Workbook

Sheet Summary
A1: ServSafe Manager (9th edition) practice question bank
B2: Every question from the class materials, one row each on the Questions sheet: question, all answer choices, correct answer,
B3: chapter (1–10) and what it tests. Use the filter arrows on row 1 to pick a chapter or source.
B4: Yellow rows: the source gives no answer, so one was assigned from ServSafe Manager 9th ed. / FDA Food Code rules
B5: (the Explanation column gives the rule). They are also listed on the Assigned answers sheet.
B6: Pink rows: the question depends on a picture that isn’t in the file, so it can’t be answered. Kept for completeness only.
B7: To quiz yourself, hide columns J–M (Correct answer, Answer from, Explanation, What it tests).
B8: The website is multiple choice only: column O shows how each question appears there, and the Website rewrites sheet
B9: shows true/false, select-all, put-in-order and fill-in questions next to their multiple-choice versions.
A11: Chapter | B11: Chapter name | C11: Kahoot Ch 4-6 | D11: SSM9E Activity Quiz 1 | E11: SSM9E Activity Quiz 2 | F11: SSM9E Activity Quiz 3 | G11: SSM9E Activity Quiz 4 | H11: SSM9E Activity Quiz 5 | I11: SSM9E Activity Quiz 6 | J11: SSM9E Activity Quiz 7 | K11: SSM9E Activity Quiz 8 | L11: SSM9E Activity Quiz 9 | M11: SSM9E Activity Quiz 10 | N11: Practice Test | O11: Diagnostic Test | P11: Mock ServSafe Test | Q11: Review Slide Deck | R11: Total | S11: Assigned answers
A12: 1 | B12: Providing Safe Food | C12: =COUNTIFS(Questions!$D$2:$D$458,$A12,Questions!$B$2:$B$458,C$11) -> 0 | D12: =COUNTIFS(Questions!$D$2:$D$458,$A12,Questions!$B$2:$B$458,D$11) -> 11 | E12: =COUNTIFS(Questions!$D$2:$D$458,$A12,Questions!$B$2:$B$458,E$11) -> 0 | F12: =COUNTIFS(Questions!$D$2:$D$458,$A12,Questions!$B$2:$B$458,F$11) -> 0 | G12: =COUNTIFS(Questions!$D$2:$D$458,$A12,Questions!$B$2:$B$458,G$11) -> 0 | H12: =COUNTIFS(Questions!$D$2:$D$458,$A12,Questions!$B$2:$B$458,H$11) -> 0 | I12: =COUNTIFS(Questions!$D$2:$D$458,$A12,Questions!$B$2:$B$458,I$11) -> 0 | J12: =COUNTIFS(Questions!$D$2:$D$458,$A12,Questions!$B$2:$B$458,J$11) -> 0 | ... Q12: =COUNTIFS(Questions!$D$2:$D$458,$A12,Questions!$B$2:$B$458,Q$11) -> 5 | R12: =SUM(C12:Q12) -> 21 | S12: =COUNTIFS(Questions!$D$2:$D$458,$A12,Questions!$K$2:$K$458,"Assigned*") -> 3
A13: 2 | B13: Forms of Contamination | C13: =COUNTIFS(Questions!$D$2:$D$458,$A13,Questions!$B$2:$B$458,C$11) -> 0 | D13: =COUNTIFS(Questions!$D$2:$D$458,$A13,Questions!$B$2:$B$458,D$11) -> 0 | E13: =COUNTIFS(Questions!$D$2:$D$458,$A13,Questions!$B$2:$B$458,E$11) -> 14 | F13: =COUNTIFS(Questions!$D$2:$D$458,$A13,Questions!$B$2:$B$458,F$11) -> 0 | G13: =COUNTIFS(Questions!$D$2:$D$458,$A13,Questions!$B$2:$B$458,G$11) -> 0 | H13: =COUNTIFS(Questions!$D$2:$D$458,$A13,Questions!$B$2:$B$458,H$11) -> 0 | I13: =COUNTIFS(Questions!$D$2:$D$458,$A13,Questions!$B$2:$B$458,I$11) -> 0 | J13: =COUNTIFS(Questions!$D$2:$D$458,$A13,Questions!$B$2:$B$458,J$11) -> 0 | ... Q13: =COUNTIFS(Questions!$D$2:$D$458,$A13,Questions!$B$2:$B$458,Q$11) -> 17 | R13: =SUM(C13:Q13) -> 48 | S13: =COUNTIFS(Questions!$D$2:$D$458,$A13,Questions!$K$2:$K$458,"Assigned*") -> 4
A14: 3 | B14: The Safe Food Handler | C14: =COUNTIFS(Questions!$D$2:$D$458,$A14,Questions!$B$2:$B$458,C$11) -> 0 | D14: =COUNTIFS(Questions!$D$2:$D$458,$A14,Questions!$B$2:$B$458,D$11) -> 0 | E14: =COUNTIFS(Questions!$D$2:$D$458,$A14,Questions!$B$2:$B$458,E$11) -> 0 | F14: =COUNTIFS(Questions!$D$2:$D$458,$A14,Questions!$B$2:$B$458,F$11) -> 11 | G14: =COUNTIFS(Questions!$D$2:$D$458,$A14,Questions!$B$2:$B$458,G$11) -> 0 | H14: =COUNTIFS(Questions!$D$2:$D$458,$A14,Questions!$B$2:$B$458,H$11) -> 0 | I14: =COUNTIFS(Questions!$D$2:$D$458,$A14,Questions!$B$2:$B$458,I$11) -> 0 | J14: =COUNTIFS(Questions!$D$2:$D$458,$A14,Questions!$B$2:$B$458,J$11) -> 0 | ... Q14: =COUNTIFS(Questions!$D$2:$D$458,$A14,Questions!$B$2:$B$458,Q$11) -> 19 | R14: =SUM(C14:Q14) -> 50 | S14: =COUNTIFS(Questions!$D$2:$D$458,$A14,Questions!$K$2:$K$458,"Assigned*") -> 11
A15: 4 | B15: The Flow of Food: An Introduction | C15: =COUNTIFS(Questions!$D$2:$D$458,$A15,Questions!$B$2:$B$458,C$11) -> 6 | D15: =COUNTIFS(Questions!$D$2:$D$458,$A15,Questions!$B$2:$B$458,D$11) -> 0 | E15: =COUNTIFS(Questions!$D$2:$D$458,$A15,Questions!$B$2:$B$458,E$11) -> 0 | F15: =COUNTIFS(Questions!$D$2:$D$458,$A15,Questions!$B$2:$B$458,F$11) -> 0 | G15: =COUNTIFS(Questions!$D$2:$D$458,$A15,Questions!$B$2:$B$458,G$11) -> 11 | H15: =COUNTIFS(Questions!$D$2:$D$458,$A15,Questions!$B$2:$B$458,H$11) -> 0 | I15: =COUNTIFS(Questions!$D$2:$D$458,$A15,Questions!$B$2:$B$458,I$11) -> 0 | J15: =COUNTIFS(Questions!$D$2:$D$458,$A15,Questions!$B$2:$B$458,J$11) -> 0 | ... Q15: =COUNTIFS(Questions!$D$2:$D$458,$A15,Questions!$B$2:$B$458,Q$11) -> 13 | R15: =SUM(C15:Q15) -> 34 | S15: =COUNTIFS(Questions!$D$2:$D$458,$A15,Questions!$K$2:$K$458,"Assigned*") -> 6
A16: 5 | B16: The Flow of Food: Purchasing, Receiving, and Storage | C16: =COUNTIFS(Questions!$D$2:$D$458,$A16,Questions!$B$2:$B$458,C$11) -> 7 | D16: =COUNTIFS(Questions!$D$2:$D$458,$A16,Questions!$B$2:$B$458,D$11) -> 0 | E16: =COUNTIFS(Questions!$D$2:$D$458,$A16,Questions!$B$2:$B$458,E$11) -> 0 | F16: =COUNTIFS(Questions!$D$2:$D$458,$A16,Questions!$B$2:$B$458,F$11) -> 0 | G16: =COUNTIFS(Questions!$D$2:$D$458,$A16,Questions!$B$2:$B$458,G$11) -> 0 | H16: =COUNTIFS(Questions!$D$2:$D$458,$A16,Questions!$B$2:$B$458,H$11) -> 12 | I16: =COUNTIFS(Questions!$D$2:$D$458,$A16,Questions!$B$2:$B$458,I$11) -> 0 | J16: =COUNTIFS(Questions!$D$2:$D$458,$A16,Questions!$B$2:$B$458,J$11) -> 0 | ... Q16: =COUNTIFS(Questions!$D$2:$D$458,$A16,Questions!$B$2:$B$458,Q$11) -> 33 | R16: =SUM(C16:Q16) -> 76 | S16: =COUNTIFS(Questions!$D$2:$D$458,$A16,Questions!$K$2:$K$458,"Assigned*") -> 5
A17: 6 | B17: The Flow of Food: Preparation | C17: =COUNTIFS(Questions!$D$2:$D$458,$A17,Questions!$B$2:$B$458,C$11) -> 11 | D17: =COUNTIFS(Questions!$D$2:$D$458,$A17,Questions!$B$2:$B$458,D$11) -> 0 | E17: =COUNTIFS(Questions!$D$2:$D$458,$A17,Questions!$B$2:$B$458,E$11) -> 0 | F17: =COUNTIFS(Questions!$D$2:$D$458,$A17,Questions!$B$2:$B$458,F$11) -> 0 | G17: =COUNTIFS(Questions!$D$2:$D$458,$A17,Questions!$B$2:$B$458,G$11) -> 0 | H17: =COUNTIFS(Questions!$D$2:$D$458,$A17,Questions!$B$2:$B$458,H$11) -> 0 | I17: =COUNTIFS(Questions!$D$2:$D$458,$A17,Questions!$B$2:$B$458,I$11) -> 12 | J17: =COUNTIFS(Questions!$D$2:$D$458,$A17,Questions!$B$2:$B$458,J$11) -> 0 | ... Q17: =COUNTIFS(Questions!$D$2:$D$458,$A17,Questions!$B$2:$B$458,Q$11) -> 8 | R17: =SUM(C17:Q17) -> 55 | S17: =COUNTIFS(Questions!$D$2:$D$458,$A17,Questions!$K$2:$K$458,"Assigned*") -> 3
A18: 7 | B18: The Flow of Food: Service | C18: =COUNTIFS(Questions!$D$2:$D$458,$A18,Questions!$B$2:$B$458,C$11) -> 0 | D18: =COUNTIFS(Questions!$D$2:$D$458,$A18,Questions!$B$2:$B$458,D$11) -> 0 | E18: =COUNTIFS(Questions!$D$2:$D$458,$A18,Questions!$B$2:$B$458,E$11) -> 0 | F18: =COUNTIFS(Questions!$D$2:$D$458,$A18,Questions!$B$2:$B$458,F$11) -> 0 | G18: =COUNTIFS(Questions!$D$2:$D$458,$A18,Questions!$B$2:$B$458,G$11) -> 0 | H18: =COUNTIFS(Questions!$D$2:$D$458,$A18,Questions!$B$2:$B$458,H$11) -> 0 | I18: =COUNTIFS(Questions!$D$2:$D$458,$A18,Questions!$B$2:$B$458,I$11) -> 0 | J18: =COUNTIFS(Questions!$D$2:$D$458,$A18,Questions!$B$2:$B$458,J$11) -> 11 | ... Q18: =COUNTIFS(Questions!$D$2:$D$458,$A18,Questions!$B$2:$B$458,Q$11) -> 10 | R18: =SUM(C18:Q18) -> 36 | S18: =COUNTIFS(Questions!$D$2:$D$458,$A18,Questions!$K$2:$K$458,"Assigned*") -> 4
A19: 8 | B19: Food Safety Management Systems | C19: =COUNTIFS(Questions!$D$2:$D$458,$A19,Questions!$B$2:$B$458,C$11) -> 0 | D19: =COUNTIFS(Questions!$D$2:$D$458,$A19,Questions!$B$2:$B$458,D$11) -> 0 | E19: =COUNTIFS(Questions!$D$2:$D$458,$A19,Questions!$B$2:$B$458,E$11) -> 0 | F19: =COUNTIFS(Questions!$D$2:$D$458,$A19,Questions!$B$2:$B$458,F$11) -> 0 | G19: =COUNTIFS(Questions!$D$2:$D$458,$A19,Questions!$B$2:$B$458,G$11) -> 0 | H19: =COUNTIFS(Questions!$D$2:$D$458,$A19,Questions!$B$2:$B$458,H$11) -> 0 | I19: =COUNTIFS(Questions!$D$2:$D$458,$A19,Questions!$B$2:$B$458,I$11) -> 0 | J19: =COUNTIFS(Questions!$D$2:$D$458,$A19,Questions!$B$2:$B$458,J$11) -> 0 | ... Q19: =COUNTIFS(Questions!$D$2:$D$458,$A19,Questions!$B$2:$B$458,Q$11) -> 5 | R19: =SUM(C19:Q19) -> 26 | S19: =COUNTIFS(Questions!$D$2:$D$458,$A19,Questions!$K$2:$K$458,"Assigned*") -> 1
A20: 9 | B20: Safe Facilities and Pest Management | C20: =COUNTIFS(Questions!$D$2:$D$458,$A20,Questions!$B$2:$B$458,C$11) -> 0 | D20: =COUNTIFS(Questions!$D$2:$D$458,$A20,Questions!$B$2:$B$458,D$11) -> 0 | E20: =COUNTIFS(Questions!$D$2:$D$458,$A20,Questions!$B$2:$B$458,E$11) -> 0 | F20: =COUNTIFS(Questions!$D$2:$D$458,$A20,Questions!$B$2:$B$458,F$11) -> 0 | G20: =COUNTIFS(Questions!$D$2:$D$458,$A20,Questions!$B$2:$B$458,G$11) -> 0 | H20: =COUNTIFS(Questions!$D$2:$D$458,$A20,Questions!$B$2:$B$458,H$11) -> 0 | I20: =COUNTIFS(Questions!$D$2:$D$458,$A20,Questions!$B$2:$B$458,I$11) -> 0 | J20: =COUNTIFS(Questions!$D$2:$D$458,$A20,Questions!$B$2:$B$458,J$11) -> 0 | ... Q20: =COUNTIFS(Questions!$D$2:$D$458,$A20,Questions!$B$2:$B$458,Q$11) -> 18 | R20: =SUM(C20:Q20) -> 59 | S20: =COUNTIFS(Questions!$D$2:$D$458,$A20,Questions!$K$2:$K$458,"Assigned*") -> 4
A21: 10 | B21: Cleaning and Sanitizing | C21: =COUNTIFS(Questions!$D$2:$D$458,$A21,Questions!$B$2:$B$458,C$11) -> 0 | D21: =COUNTIFS(Questions!$D$2:$D$458,$A21,Questions!$B$2:$B$458,D$11) -> 0 | E21: =COUNTIFS(Questions!$D$2:$D$458,$A21,Questions!$B$2:$B$458,E$11) -> 0 | F21: =COUNTIFS(Questions!$D$2:$D$458,$A21,Questions!$B$2:$B$458,F$11) -> 0 | G21: =COUNTIFS(Questions!$D$2:$D$458,$A21,Questions!$B$2:$B$458,G$11) -> 0 | H21: =COUNTIFS(Questions!$D$2:$D$458,$A21,Questions!$B$2:$B$458,H$11) -> 0 | I21: =COUNTIFS(Questions!$D$2:$D$458,$A21,Questions!$B$2:$B$458,I$11) -> 0 | J21: =COUNTIFS(Questions!$D$2:$D$458,$A21,Questions!$B$2:$B$458,J$11) -> 0 | ... Q21: =COUNTIFS(Questions!$D$2:$D$458,$A21,Questions!$B$2:$B$458,Q$11) -> 23 | R21: =SUM(C21:Q21) -> 52 | S21: =COUNTIFS(Questions!$D$2:$D$458,$A21,Questions!$K$2:$K$458,"Assigned*") -> 2
A22: Total | C22: =SUM(C12:C21) -> 24 | D22: =SUM(D12:D21) -> 11 | E22: =SUM(E12:E21) -> 14 | F22: =SUM(F12:F21) -> 11 | G22: =SUM(G12:G21) -> 11 | H22: =SUM(H12:H21) -> 12 | I22: =SUM(I12:I21) -> 12 | J22: =SUM(J12:J21) -> 11 | ... S22: =SUM(S12:S21) -> 43

Sheet Questions
A1: ID | B1: Source | C1: Where in source | D1: Chapter | E1: Chapter name | F1: Topic | G1: Question type | H1: Question | I1: Answer choices | J1: Correct answer | K1: Answer from | L1: Explanation | M1: What it tests | N1: Note | O1: On the website as
A2: KH-02 | B2: Kahoot Ch 4-6 | C2: Q2 | D2: 4 | E2: The Flow of Food: An Introduction | F2: Preventing cross-contamination | G2: Multiple choice | H2: Using one set of cutting boards for raw poultry and another set of cutting boards for RTE food reduces the risk of | I2: A. cross-contamination. B. time-temperature abuse. C. physical contamination. D. toxic-metal poison | J2: A. cross-contamination. | K2: Source | L2: Separate cutting boards for raw poultry and ready-to-eat food keep pathogens from raw food from spreading to food that won’t be cooked. | M2: Link separate equipment to preventing cross-contamination. Time-temperature abuse and physical contamination are different hazards used as traps. | N2: Same question as MT-16. | O2: Multiple choice
A3: KH-03 | B3: Kahoot Ch 4-6 | C3: Q3 | D3: 4 | E3: The Flow of Food: An Introduction | F3: Temperature danger zone and time-temperature abuse | G3: Multiple choice | H3: Pathogens are likely to grow well in a meat stew that is | I3: A. below freezing temperature. B. at refrigeration temperatures. C. between 41°F and 135°F (5°C and 57°C). D. cooked to the correct internal temperature. | J3: C. between 41°F and 135°F (5°C and 57°C). | K3: Source | L3: Pathogens grow well between 41°F and 135°F (5°C and 57°C), the temperature danger zone. | M3: Recall the temperature danger zone, 41–135°F (5–57°C). Freezing, refrigeration and correct cooking all slow or stop growth. | O3: Multiple choice
A4: KH-04 | B4: Kahoot Ch 4-6 | C4: Q4 | D4: 4 | E4: The Flow of Food: An Introduction | F4: Thermometers and calibration | G4: Multiple choice | H4: What is the calibration nut on a bimetallic stemmed thermometer used for? | I4: A. To mark its sensing area B. To measure air temperature C. To keep it accurate D. To measure temperatures through glass | J4: C. To keep it accurate | K4: Source | L4: The calibration nut on a bimetallic stemmed thermometer is used to adjust it so its readings stay accurate. | M4: Know the parts of a bimetallic stemmed thermometer: the calibration nut keeps it accurate, while the dimple marks the sensing area (the trap). | O4: Multiple choice
A5: KH-05 | B5: Kahoot Ch 4-6 | C5: Q5 | D5: 4 | E5: The Flow of Food: An Introduction | F5: Thermometers and calibration | G5: Multiple choice | H5: Which probe should be used to check the temperature of a pork roast? | I5: A. Air B. Surface C. Immersion D. Penetration | J5: D. Penetration | K5: Source | L5: A penetration probe is used to check the internal temperature of thick food such as a roast. | M5: Match probe types to uses: penetration for thick food, immersion for liquids, surface for flat cooking equipment, air for coolers and ovens. | O5: Multiple choice
A6: KH-06 | B6: Kahoot Ch 4-6 | C6: Q6 | D6: 4 | E6: The Flow of Food: An Introduction | F6: Thermometers and calibration | G6: Multiple choice | H6: What do time-temperature indicators do? | I6: A. Measure temperature through a probe with a sensor at the end B. Measure the length of time that food should be cooked C. Show if food has been cross-contaminated during preparation D. Show if food has been time-temperature abused during shipment | J6: D. Show if food has been time-temperature abused during shipment | K6: Source | L6: Time-temperature indicators (TTIs) change color permanently if food has been time-temperature abused during shipment or storage. | M6: Know what a TTI does: shows past time-temperature abuse. It does not measure temperature through a probe or detect cross-contamination. | O6: Multiple choice
A7: KH-07 | B7: Kahoot Ch 4-6 | C7: Q7 | D7: 4 | E7: The Flow of Food: An Introduction | F7: Thermometers and calibration | G7: Multiple choice | H7: When using the ice-point method to calibrate a thermometer, to what temperature should the thermometer be adjusted? | I7: A. 32°F (0°C) B. 0°F (-18°C) C. 41°F (5°C) D. 212°F (100°C) | J7: A. 32°F (0°C) | K7: Source | L7: In the ice-point method, a thermometer in ice water is adjusted to read 32°F (0°C). | M7: Recall the ice-point calibration temperature, 32°F (0°C). 212°F (100°C) is the boiling-point method, and 41°F is the cold-holding limit. | O7: Multiple choice
A8: KH-09 | B8: Kahoot Ch 4-6 | C8: Q9 | D8: 5 | E8: The Flow of Food: Purchasing, Receiving, and Storage | F8: Approved suppliers and recalls | G8: Multiple choice | H8: What must a manager do with a recalled food item in the operation? | I8: A. Combine the item with non-recalled items during preparation B. Record the names of customers who purchase the item C. Store the recalled item separately from other food D. Sell all recalled items within 24 hours | J8: C. Store the recalled item separately from other food | K8: Source | L8: A recalled item must be stored separately from other food (and labeled) so it isn’t used or sold. | M8: Know the recall procedure: separate and label the item. Mixing it with other food, selling it quickly or tracking customers are the traps. | N8: Same question as DT-80. | O8: Multiple choice
A9: KH-10 | B9: Kahoot Ch 4-6 | C9: Q10 | D9: 5 | E9: The Flow of Food: Purchasing, Receiving, and Storage | F9: Receiving: packaging, documents and quality | G9: Multiple choice | H9: What are the packaging criteria for accepting nonfood items? | I9: A. Soiled but intact B. Clean and no more than two tears or punctures C. Soiled and no more than two tears or punctures D. Intact, clean, and protected from contamination | J9: D. Intact, clean, and protected from contamination | K9: Source | L9: Nonfood items must arrive in packaging that is intact, clean and protects them from contamination. | M9: Recall the packaging rule for nonfood items: intact and clean. Any soiled or torn packaging is grounds to reject. | O9: Multiple choice
A10: KH-11 | B10: Kahoot Ch 4-6 | C10: Q11 | D10: 5 | E10: The Flow of Food: Purchasing, Receiving, and Storage | F10: Storage temperature, rotation and order | G10: Multiple choice | H10: Supplies should be stored away from the walls and at least ________ off the floor. | I10: A. 2 inches (5 centimeters) B. 4 inches (10 centimeters) C. 5 inches (13 centimeters) D. 6 inches (15 centimeters) | J10: D. 6 inches (15 centimeters) | K10: Source | L10: Food and supplies must be stored away from walls and at least 6 inches (15 centimeters) off the floor. | M10: Recall the 6-inch (15 cm) rule for storage. Smaller distances are traps. | N10: Similar to DT-32. | O10: Multiple choice
A11: KH-12 | B11: Kahoot Ch 4-6 | C11: Q12 | D11: 5 | E11: The Flow of Food: Purchasing, Receiving, and Storage | F11: Labeling and date marking | G11: Multiple choice | H11: Ready-to-eat TCS food must be date marked if it will be held for longer than | I11: A. 12 hours. B. 24 hours. C. 36 hours. D. 48 hours. | J11: B. 24 hours. | K11: Source | L11: Ready-to-eat TCS food held for longer than 24 hours must be date-marked. | M11: Recall the 24-hour date-marking trigger. The other hour values are traps. | N11: Same question as MT-05; similar to DT-44. | O11: Multiple choice
A12: KH-13 | B12: Kahoot Ch 4-6 | C12: Q13 | D12: 5 | E12: The Flow of Food: Purchasing, Receiving, and Storage | F12: Storage temperature, rotation and order | G12: Multiple choice | H12: Which item is stored correctly in a cooler? | I12: A. Macaroni salad stored above raw salmon B. Raw ground pork stored below raw poultry C. Raw poultry stored above raw pork roast D. Sliced pineapple stored below raw steaks | J12: A. Macaroni salad stored above raw salmon | K12: Source | L12: Ready-to-eat food goes above raw food, and raw food is stored top to bottom by cooking temperature, with poultry on the bottom. | M12: Apply the cooler storage order. Each trap puts a raw item above something that should be higher, such as poultry above pork or raw steak over pineapple. | N12: Same question as MT-12. | O12: Multiple choice
A13: KH-14 | B13: Kahoot Ch 4-6 | C13: Q14 | D13: 5 | E13: The Flow of Food: Purchasing, Receiving, and Storage | F13: Receiving: packaging, documents and quality | G13: Multiple choice | H13: A food item that is received with an expired use-by date should be | I13: A. used immediately. B. accepted but labeled differently C. accepted but kept separate from other items. D. Rejected | J13: D. Rejected | K13: Source | L13: Food that arrives past its use-by or expiration date must be rejected. | M13: Know the receiving rule for expired dates: reject. Accepting it with a new label or keeping it separate are traps. | O13: Multiple choice
A14: KH-15 | B14: Kahoot Ch 4-6 | C14: Q15 | D14: 5 | E14: The Flow of Food: Purchasing, Receiving, and Storage | F14: Receiving temperatures | G14: Multiple choice | H14: Milk can be received at 45°F (7°C) under what conditions? | I14: A. It is thrown out after 2 days B. It is immediately cooled to 41°F (5°C) or lower C. It is cooled to 41°F (5°C) or lower in 4 hours D. It is served or used in the operation within 2 hours | J14: C. It is cooled to 41°F (5°C) or lower in 4 hours | K14: Source | L14: Milk may be received at 45°F (7°C) or lower, but must then be cooled to 41°F (5°C) or lower within four hours. | M14: Recall the milk receiving exception and its four-hour cooling window. Traps: cooling immediately, discarding after two days, or a two-hour use rule. | O14: Multiple choice
A15: KH-17 | B15: Kahoot Ch 4-6 | C15: Q17 | D15: 6 | E15: The Flow of Food: Preparation | F15: Prepping specific foods and variances | G15: Multiple choice | H15: Which food must be separated from ready-to-eat food? | I15: A. Raw nuts B. Hard cheeses C. Washed and peeled produce D. Unwashed fruits and vegetables | J15: D. Unwashed fruits and vegetables | K15: Source | L15: Unwashed fruits and vegetables can carry soil and pathogens, so they must be kept separate from ready-to-eat food. | M15: Know which produce needs separating: unwashed. Washed, peeled produce, hard cheese and raw nuts are not the cross-contamination risk here. | O15: Multiple choice
A16: KH-18 | B16: Kahoot Ch 4-6 | C16: Q18 | D16: 6 | E16: The Flow of Food: Preparation | F16: Prepping specific foods and variances | G16: Multiple choice | H16: A variance from the local regulatory authority is needed for | I16: A. smoking food to preserve it. B. developing a crisis-management plan. C. using TCS leftovers to make salads. D. using ice to cool food. | J16: A. smoking food to preserve it. | K16: Source | L16: A variance is required for special processes such as smoking food as a way to preserve it (not just for flavor). | M16: Recall which processes need a variance: smoking or curing to preserve, using additives, ROP, sprouting seeds and similar. Ice cooling and crisis plans don’t need one. | O16: Multiple choice
A17: KH-19 | B17: Kahoot Ch 4-6 | C17: Q19 | D17: 6 | E17: The Flow of Food: Preparation | F17: Thawing | G17: Multiple choice | H17: What is one way that food should NEVER be thawed? | I17: A. In a microwave B. In a cooler C. At room temperature D. As part of the cooking process | J17: C. At room temperature | K17: Source | L17: Food should never be thawed at room temperature because its surface sits in the temperature danger zone. | M17: Know the four safe thawing methods and spot the unsafe one: room temperature. Microwave, cooler and cooking are all approved. | O17: Multiple choice
A18: KH-20 | B18: Kahoot Ch 4-6 | C18: Q20 | D18: 6 | E18: The Flow of Food: Preparation | F18: Minimum internal cooking temperatures | G18: Multiple choice | H18: What is the required minimum internal cooking temperature for a chicken breast? | I18: A. 135°F (57°C) B. 145°F (63°C) for 15 seconds C. 155°F (68°C) for 17 seconds D. 165°F (74°C) for <1 second | J18: D. 165°F (74°C) for <1 second | K18: Source | L18: Poultry, including a chicken breast, must be cooked to 165°F (74°C) for less than 1 second (instantaneous). | M18: Recall the poultry cooking temperature, 165°F (74°C). 155°F is for ground meat and 145°F for seafood and whole cuts, which are the traps. | O18: Multiple choice
A19: KH-21 | B19: Kahoot Ch 4-6 | C19: Q21 | D19: 6 | E19: The Flow of Food: Preparation | F19: Cooling and reheating | G19: Multiple choice | H19: What temperature must soup that contains cooked beef be reheated to for hot holding? | I19: A. 135°F (57°C) for 15 seconds B. 145°F (63°C) for 15 seconds C. 155°F (68°C) for 15 seconds D. 165°F (74°C) for 15 seconds | J19: D. 165°F (74°C) for 15 seconds | K19: Source | L19: TCS food reheated for hot holding must reach 165°F (74°C) for 15 seconds within two hours, even though the beef was already cooked. | M19: Recall the reheating-for-hot-holding temperature: 165°F for 15 seconds. The trap is thinking cooked beef only needs its original cooking temperature. | N19: Similar to DT-41 and PT-23. | O19: Multiple choice
A20: KH-22 | B20: Kahoot Ch 4-6 | C20: Q22 | D20: 6 | E20: The Flow of Food: Preparation | F20: Consumer advisories and high-risk menus | G20: Multiple choice | H20: Which food item would the FDA advise against offering on a children's menu? | I20: A. Rare cheeseburgers B. Peanut butter and jelly sandwiches C. Cheese pizza D. Fried shrimp | J20: A. Rare cheeseburgers | K20: Source | L20: Operations serving high-risk groups such as young children should not offer raw or undercooked animal food, like rare burgers. | M20: Tests the high-risk population rule: no raw or undercooked meat on a children’s menu. PB&J and peanuts raise allergen questions, not undercooking. | O20: Multiple choice
A21: KH-23 | B21: Kahoot Ch 4-6 | C21: Q23 | D21: 6 | E21: The Flow of Food: Preparation | F21: Minimum internal cooking temperatures | G21: Multiple choice | H21: When checking the internal temperature of food, where should the thermometer be inserted? | I21: A. In the thinnest part of the food B. In the thickest part of the food C. On the bottom of the food D. On the top of the food | J21: B. In the thickest part of the food | K21: Source | L21: Insert the thermometer into the thickest part of the food, which is the last part to heat. | M21: Know where to take the temperature: the thickest part. Thinnest, top and bottom readings can be misleadingly high. | N21: Similar to DT-35 and MT-35. | O21: Multiple choice
A22: KH-24 | B22: Kahoot Ch 4-6 | C22: Q24 | D22: 6 | E22: The Flow of Food: Preparation | F22: Minimum internal cooking temperatures | G22: Multiple choice | H22: What is the required minimum internal cooking temperature for ground beef? | I22: A. 135°F (57°C) B. 145°F (63°C) for 15 seconds C. 155°F (68°C) for 17 seconds D. 165°F (74°C) for < 1 seconds | J22: C. 155°F (68°C) for 17 seconds | K22: Source | L22: Ground beef must be cooked to 155°F (68°C) for 17 seconds. | M22: Recall the ground meat cooking temperature, 155°F (68°C) for 17 seconds. 145°F is for whole cuts and 165°F for poultry. | N22: Similar to PT-17. | O22: Multiple choice
A23: KH-25 | B23: Kahoot Ch 4-6 | C23: Q25 | D23: 6 | E23: The Flow of Food: Preparation | F23: Thawing | G23: Multiple choice | H23: What must you do immediately after thawing food in a microwave? | I23: A. Cool it B. Cook it C. Hold it D. Freeze it | J23: B. Cook it | K23: Source | L23: Food thawed in a microwave must be cooked immediately afterward, because parts of it may have warmed into the danger zone. | M23: Know the microwave thawing rule: cook it right away. Holding, cooling or refreezing it are traps. | O23: Multiple choice
A24: KH-26 | B24: Kahoot Ch 4-6 | C24: Q26 | D24: 6 | E24: The Flow of Food: Preparation | F24: Consumer advisories and high-risk menus | G24: Multiple choice | H24: A consumer advisory should be provided for menu items that contain TCS food that | I24: A. is very spicy. B. contains gluten. C. is raw or undercooked. D. is made with a Big Nine allergen. | J24: C. is raw or undercooked. | K24: Source | L24: A consumer advisory is required when TCS food is served raw or undercooked. | M24: Recall the trigger for a consumer advisory: raw or undercooked TCS food. Allergens are handled by allergen notification, a different requirement. | N24: Similar to DT-51. | O24: Multiple choice
A25: KH-27 | B25: Kahoot Ch 4-6 | C25: Q27 | D25: 6 | E25: The Flow of Food: Preparation | F25: Cooling and reheating | G25: Multiple choice | H25: Food was cooled from 135°F to 70°F (57°C to 21°C) in 1 hour, then the food must cool from 70°F to 41°F (21°C to 5°C) within | I25: A. 4 hours B. 6 hours C. 2 hours D. 5 hours | J25: D. 5 hours | K25: Source | L25: Total cooling time is six hours, with no more than two for the first stage. If the first stage took one hour, five hours remain to reach 41°F (5°C). | M25: Apply the six-hour total: time saved in the first stage carries over to the second. The trap is assuming the second stage is always exactly four hours. | N25: Similar to DT-39. | O25: Multiple choice
A26: AQ01-01 | B26: SSM9E Activity Quiz 1 | C26: True or False #1 | D26: 1 | E26: Providing Safe Food | F26: How food becomes unsafe | G26: True / false | H26: A food handler’s hands can transfer pathogens from one food to another. | I26: A. True B. False | J26: True | K26: Source | L26: Hands that touch raw food, the body or dirty surfaces can carry pathogens to the next food they touch. | M26: Knowing that hands are a common route for moving pathogens between foods, which is why handwashing and glove changes matter. | O26: Multiple choice (rewritten)
A27: AQ01-02 | B27: SSM9E Activity Quiz 1 | C27: True or False #2 | D27: 1 | E27: Providing Safe Food | F27: How food becomes unsafe | G27: True / false | H27: Food handlers who don’t wash their hands correctly can cause a foodborne illness. | I27: A. True B. False | J27: True | K27: Source | L27: Pathogens on unwashed hands get into food and can make people sick. | M27: Linking poor personal hygiene, one of the ways food becomes unsafe, to actual illness. | O27: Multiple choice (rewritten)
A28: AQ01-03 | B28: SSM9E Activity Quiz 1 | C28: True or False #3 | D28: 1 | E28: Providing Safe Food | F28: Foodborne illness and high-risk groups | G28: True / false | H28: A foodborne-illness outbreak is when two or more people get sick after eating at the same place. | I28: A. True B. False | J28: False | K28: Source | L28: An outbreak is two or more people with the same symptoms after eating the same food, investigated and confirmed by regulators and lab analysis. | M28: Knowing the outbreak definition: the trap is “same place.” It takes two or more people with the same symptoms after eating the same food, confirmed by investigation. | O28: Multiple choice (rewritten)
A29: AQ01-04 | B29: SSM9E Activity Quiz 1 | C29: True or False #4 | D29: 1 | E29: Providing Safe Food | F29: Foodborne illness and high-risk groups | G29: True / false | H29: Adults are more likely than preschool-age children to get sick from contaminated food. | I29: A. True B. False | J29: False | K29: Source | L29: Preschool-age children are a high-risk population; healthy adults are not. | M29: Recognizing high-risk populations: preschool-age children are more likely to get sick because their immune systems are not fully developed. | O29: Multiple choice (rewritten)
A30: AQ01-05 | B30: SSM9E Activity Quiz 1 | C30: True or False #5 | D30: 1 | E30: Providing Safe Food | F30: Manager role, training and inspections | G30: True / false | H30: Training needs can be identified by watching employee performance. | I30: A. True B. False | J30: True | K30: Source | L30: Watching employees work (along with tests and inspection results) shows where training is needed. | M30: Knowing how managers find training needs: observing staff at work shows what they are doing wrong. | O30: Multiple choice (rewritten)
A31: AQ01-06 | B31: SSM9E Activity Quiz 1 | C31: How Food Becomes Unsafe #1 | D31: 1 | E31: Providing Safe Food | F31: How food becomes unsafe | G31: Multiple choice | H31: Leftover chili is cooled on the counter. How did the food become unsafe? | I31: A. Cross-contamination B. Poor personal hygiene C. Time-temperature abuse D. Poor cleaning and sanitizing | J31: C. Time-temperature abuse | K31: Source | L31: Food cooled on a counter does not pass through the temperature danger zone fast enough. | M31: Spotting time-temperature abuse: cooling at room temperature leaves food in the temperature danger zone too long. | O31: Multiple choice
A32: AQ01-07 | B32: SSM9E Activity Quiz 1 | C32: How Food Becomes Unsafe #2 | D32: 1 | E32: Providing Safe Food | F32: How food becomes unsafe | G32: Multiple choice | H32: A food handler wearing gloves places a chicken breast on the grill and then places lettuce and tomato on a bun. How did the food become unsafe? | I32: A. Cross-contamination B. Poor personal hygiene C. Time-temperature abuse D. Poor cleaning and sanitizing | J32: A. Cross-contamination | K32: Source | L32: Pathogens moved from the raw chicken to the lettuce and tomato on the same gloves; gloves must be changed between raw and ready-to-eat food. | M32: Recognizing cross-contamination: the same gloves carried pathogens from raw chicken to ready-to-eat produce. Gloves don’t help if they aren’t changed between tasks. | O32: Multiple choice
A33: AQ01-08 | B33: SSM9E Activity Quiz 1 | C33: How Food Becomes Unsafe #3 | D33: 1 | E33: Providing Safe Food | F33: How food becomes unsafe | G33: Multiple choice | H33: A food handler prepping a salad stops to scratch an itch on her arm and then returns to making the salad. How did the food become unsafe? | I33: A. Cross-contamination B. Poor personal hygiene C. Time-temperature abuse D. Poor cleaning and sanitizing | J33: B. Poor personal hygiene | K33: Source | L33: Touching skin can pick up pathogens; hands must be washed before going back to food. | M33: Recognizing poor personal hygiene: touching the body and then food without washing hands. | O33: Multiple choice
A34: AQ01-09 | B34: SSM9E Activity Quiz 1 | C34: How Food Becomes Unsafe #4 | D34: 1 | E34: Providing Safe Food | F34: How food becomes unsafe | G34: Multiple choice | H34: After prepping raw chicken on a cutting board, a food handler wipes the board with a towel and then uses it to slice tomatoes for a salad. How did the food become unsafe? | I34: A. Cross-contamination B. Poor personal hygiene C. Time-temperature abuse D. Poor cleaning and sanitizing | J34: D. Poor cleaning and sanitizing | K34: Source | L34: A food-contact surface must be cleaned and sanitized, not just wiped, between raw meat and ready-to-eat food. | M34: Telling poor cleaning and sanitizing apart from cross-contamination: the root problem is that wiping is not cleaning and sanitizing the board. | O34: Multiple choice
A35: AQ01-10 | B35: SSM9E Activity Quiz 1 | C35: How Food Becomes Unsafe #5 | D35: 1 | E35: Providing Safe Food | F35: Manager role, training and inspections | G35: Multiple choice | H35: What is the purpose of a regulatory health inspection? | I35: A. To certify employees in food handling procedures B. To ensure that an operation is meeting minimum food safety standards C. To rate the cleanliness of the establishment for public display D. To recognize establishments that exceed food safety expectations | J35: B. To ensure that an operation is meeting minimum food safety standards | K35: Source | L35: Regulatory inspections check that an operation meets the minimum standards of the food code. | M35: Knowing what inspections are for: checking that the operation meets minimum food safety standards, not certifying staff or rating the restaurant publicly. | O35: Multiple choice
A36: AQ01-11 | B36: SSM9E Activity Quiz 1 | C36: TCS Food | D36: 1 | E36: Providing Safe Food | F36: TCS and ready-to-eat food | G36: Select all that apply | H36: Which of these foods is, or contains, a TCS food? Select every one that applies. | I36: A. Baked potatoes B. Orange juice C. Pizza with diced tomatoes and green pepper D. Poached salmon E. Refried beans F. Scrambled shell eggs G. Shrimp fried rice H. Tofu ice cream I. Vanilla milk shake J. Whole-wheat bread | J36: A, C, D, E, F, G, H, I: Baked potatoes; Pizza with diced tomatoes and green pepper; Poached salmon; Refried beans; Scrambled shell eggs; Shrimp fried rice; Tofu ice cream; Vanilla milk shake | K36: Source | L36: TCS foods include cooked rice, potatoes and beans; cut tomatoes; seafood; eggs; tofu and soy protein; and milk and dairy products. | M36: Recognizing TCS foods: cooked starches and vegetables, cut tomatoes, fish, beans, eggs, rice, tofu and dairy all need time and temperature control. Orange juice and bread do not. | O36: Multiple choice (rewritten)
A37: AQ02-01 | B37: SSM9E Activity Quiz 2 | C37: True or False #1 | D37: 2 | E37: Forms of Contamination | F37: Pathogen growth (FAT TOM) | G37: True / false | H37: All pathogens need oxygen to grow. | I37: A. True B. False | J37: False | K37: Source | L37: Some pathogens need oxygen, but others grow without it (for example in reduced-oxygen packaging or cooked rice). | M37: Knowing the O in FAT TOM: some pathogens need oxygen and others grow without it. The trap is the word “all.” | O37: Multiple choice (rewritten)
... A42: AQ02-06 | B42: SSM9E Activity Quiz 2 | C42: True or False #6 | D42: 2 | E42: Forms of Contamination | F42: Food allergens and cross-contact | G42: True / false | H42: A restaurant must use table tents to notify people of the major allergens in their food. | I42: A. True B. False | J42: False | K42: Source | L42: Customers must be told about major allergens, but table tents are only one acceptable way to do it. | M42: Knowing that allergen notification can take several written forms (menus, placards, table tents, brochures); no single method is required. Watch for “must.” | O42: Multiple choice (rewritten)
A43: AQ02-07 | B43: SSM9E Activity Quiz 2 | C43: Pathogen Growth | D43: 2 | E43: Forms of Contamination | F43: Pathogen growth (FAT TOM) | G43: List | H43: List the six conditions that pathogens need to grow. | J43: Food; Acidity; Temperature; Time; Oxygen; Moisture | K43: Source | L43: FAT TOM: Food, Acidity, Temperature, Time, Oxygen, Moisture. | M43: Recalling FAT TOM, the six conditions that let pathogens grow, which are also the levers used to control them. | O43: Knowledge point
A44: AQ02-08 | B44: SSM9E Activity Quiz 2 | C44: Pathogens and Linked Food #1 | D44: 2 | E44: Forms of Contamination | F44: Big Six pathogens and linked foods | G44: Select all that apply | H44: Which foods are commonly linked with Hepatitis A? Select every one that applies. | I44: A. Beverages B. Eggs and poultry C. Meat D. Fish E. Shellfish F. Ready-to-eat food G. Produce H. Rice/grains I. Milk/dairy products J. Contaminated water | J44: E, F, J: Shellfish; Ready-to-eat food; Contaminated water | K44: Source | L44: Hepatitis A is linked with ready-to-eat food, shellfish from contaminated water, and contaminated water. | M44: Matching Hepatitis A to its foods: shellfish from contaminated water, ready-to-eat food and contaminated water. It spreads through feces on hands, so RTE food is key. | O44: Multiple choice (rewritten)
A45: AQ02-09 | B45: SSM9E Activity Quiz 2 | C45: Pathogens and Linked Food #2 | D45: 2 | E45: Forms of Contamination | F45: Big Six pathogens and linked foods | G45: Select all that apply | H45: Which foods are commonly linked with Norovirus? Select every one that applies. | I45: A. Beverages B. Eggs and poultry C. Meat D. Fish E. Shellfish F. Ready-to-eat food G. Produce H. Rice/grains I. Milk/dairy products J. Contaminated water | J45: E, F, J: Shellfish; Ready-to-eat food; Contaminated water | K45: Source | L45: Norovirus is linked with ready-to-eat food, shellfish from contaminated water, and contaminated water. | M45: Matching Norovirus to the same foods as Hepatitis A (shellfish, ready-to-eat food, water): both viruses spread through feces on hands and contaminated water. | O45: Multiple choice (rewritten)
A46: AQ02-10 | B46: SSM9E Activity Quiz 2 | C46: Pathogens and Linked Food #3 | D46: 2 | E46: Forms of Contamination | F46: Big Six pathogens and linked foods | G46: Select all that apply | H46: Which foods are commonly linked with Salmonella Typhi? Select every one that applies. | I46: A. Beverages B. Eggs and poultry C. Meat D. Fish E. Shellfish F. Ready-to-eat food G. Produce H. Rice/grains I. Milk/dairy products J. Contaminated water | J46: A, F: Beverages; Ready-to-eat food | K46: Source | L46: Salmonella Typhi lives only in humans and is linked with ready-to-eat food and beverages. | M46: Matching Salmonella Typhi to ready-to-eat food and beverages. Don’t confuse it with nontyphoidal Salmonella, which is linked with poultry, eggs, meat, dairy and produce. | O46: Multiple choice (rewritten)
A47: AQ02-11 | B47: SSM9E Activity Quiz 2 | C47: Pathogens and Linked Food #4 | D47: 2 | E47: Forms of Contamination | F47: Big Six pathogens and linked foods | G47: Select all that apply | H47: Which foods are commonly linked with Shigella spp.? Select every one that applies. | I47: A. Beverages B. Eggs and poultry C. Meat D. Fish E. Shellfish F. Ready-to-eat food G. Produce H. Rice/grains I. Milk/dairy products J. Contaminated water | J47: F, G, J: Ready-to-eat food; Produce; Contaminated water | K47: Source | L47: Shigella spp. is linked with food easily contaminated by hands, such as salads, and with produce and contaminated water. | M47: Matching Shigella spp. to foods easily contaminated by hands (ready-to-eat food, produce) and to contaminated water. | O47: Multiple choice (rewritten)
A48: AQ02-12 | B48: SSM9E Activity Quiz 2 | C48: Pathogens and Linked Food #5 | D48: 2 | E48: Forms of Contamination | F48: Big Six pathogens and linked foods | G48: Select all that apply | H48: Which foods are commonly linked with Shiga toxin-producing Escherichia coli (STEC)? Select every one that applies. | I48: A. Beverages B. Eggs and poultry C. Meat D. Fish E. Shellfish F. Ready-to-eat food G. Produce H. Rice/grains I. Milk/dairy products J. Contaminated water | J48: C, G: Meat; Produce | K48: Source | L48: STEC is found in the intestines of cattle and is linked with ground beef and contaminated produce. | M48: Matching STEC to raw ground beef (meat) and contaminated produce; it lives in the intestines of cattle. | O48: Multiple choice (rewritten)
A49: AQ02-13 | B49: SSM9E Activity Quiz 2 | C49: Pathogens and Linked Food #6 | D49: 2 | E49: Forms of Contamination | F49: Big Six pathogens and linked foods | G49: Select all that apply | H49: Which foods are commonly linked with nontyphoidal Salmonella? Select every one that applies. | I49: A. Beverages B. Eggs and poultry C. Meat D. Fish E. Shellfish F. Ready-to-eat food G. Produce H. Rice/grains I. Milk/dairy products J. Contaminated water | J49: B, C, G, I: Eggs and poultry; Meat; Produce; Milk/dairy products | K49: Source | L49: Many farm animals carry nontyphoidal Salmonella; it is linked with poultry and eggs, meat, milk and dairy products, and produce. | M49: Matching nontyphoidal Salmonella to animal foods carried by farm animals (poultry, eggs, meat, dairy) plus produce. | O49: Multiple choice (rewritten)
A50: AQ02-14 | B50: SSM9E Activity Quiz 2 | C50: Contaminants | D50: 2 | E50: Forms of Contamination | F50: Chemical and physical contaminants | G50: List | H50: What are the three types of contaminants that are a risk to food? Give an example of each. | J50: Biological: bacteria, viruses, parasites, fungi, or toxins from plants, mushrooms and seafood; Physical: foreign objects such as dirt, broken glass, metal staples or bones; Chemical: cleaners, sanitizers or polishes | K50: Source | L50: Contaminants are biological, chemical or physical. | M50: Recalling the three contaminant types and being able to give a real example of each. | O50: Knowledge point
A51: AQ03-01 | B51: SSM9E Activity Quiz 3 | C51: True or False #1 | D51: 3 | E51: The Safe Food Handler | F51: Handwashing and hand care | G51: True / false | H51: You should wash your hands after taking a break to smoke. | I51: A. True B. False | J51: True | K51: Source | L51: Smoking puts hands near the mouth; wash hands before returning to work. | M51: Knowing when to wash hands: after smoking, eating, drinking or chewing gum, before going back to food. | O51: Multiple choice (rewritten)
A52: AQ03-02 | B52: SSM9E Activity Quiz 3 | C52: True or False #2 | D52: 3 | E52: The Safe Food Handler | F52: Handwashing and hand care | G52: True / false | H52: You should not have painted fingernails when prepping food. | I52: A. True B. False | J52: True | K52: Source | L52: Nail polish can disguise dirt under the nails and can flake off into food. | M52: Knowing hand-care rules: nail polish can hide dirt and flake into food (unless gloves are worn over it). | O52: Multiple choice (rewritten)
A53: AQ03-03 | B53: SSM9E Activity Quiz 3 | C53: True or False #3 | D53: 3 | E53: The Safe Food Handler | F53: Work attire and personal behaviors | G53: True / false | H53: Wearing a dirty uniform or apron can contaminate food. | I53: A. True B. False | J53: True | K53: Source | L53: Dirty clothing may hold pathogens; wear clean clothing every day and change aprons when they get dirty. | M53: Knowing why work attire matters: dirty clothes carry pathogens that can reach food. | O53: Multiple choice (rewritten)
A54: AQ03-04 | B54: SSM9E Activity Quiz 3 | C54: True or False #4 | D54: 3 | E54: The Safe Food Handler | F54: Handwashing and hand care | G54: True / false | H54: Use hand antiseptic before washing hands. | I54: A. True B. False | J54: False | K54: Source | L54: Hand antiseptics must be used only after handwashing, never in place of it. | M54: Knowing that hand antiseptic is used only after correct handwashing, never before or instead of it. | O54: Multiple choice (rewritten)
A55: AQ03-05 | B55: SSM9E Activity Quiz 3 | C55: True or False #5 | D55: 3 | E55: The Safe Food Handler | F55: Gloves and bare-hand contact | G55: True / false | H55: Cut-resistant gloves must be smooth and nonabsorbent. | I55: A. True B. False | J55: True | K55: Source | L55: Cut-resistant gloves must have a smooth, durable, nonabsorbent surface, or be covered with a single-use glove, when used with ready-to-eat food. | M55: Knowing the surface rule for cut-resistant gloves so they can be kept clean and don’t hold pathogens. | N55: The FDA Food Code applies this rule when cut-resistant gloves touch ready-to-eat food; otherwise they may be covered with a single-use glove. The quiz key marks it True. | O55: Multiple choice (rewritten)
A56: AQ03-06 | B56: SSM9E Activity Quiz 3 | C56: Handwashing Steps | D56: 3 | E56: The Safe Food Handler | F56: Handwashing and hand care | G56: Put in order | H56: Put the handwashing steps in the correct order. | I56: A. Vigorously scrub hands and arms for at least 10 to 15 seconds. B. Apply enough soap to build up a good lather. C. Dry hands and arms with a single-use paper towel or a hand dryer. D. Wet your hands and arms with warm running water. E. Rinse your hands and arms thoroughly under warm running water. | J56: 1. Wet your hands and arms with warm running water. (D); 2. Apply enough soap to build up a good lather. (B); 3. Vigorously scrub hands and arms for at least 10 to 15 seconds. (A); 4. Rinse your hands and arms thoroughly under warm running water. (E); 5. Dry hands and arms with a single-use paper towel or a hand dryer. (C) | K56: Source | L56: Wet with warm running water, apply soap, scrub 10 to 15 seconds, rinse, then dry; the whole process takes at least 20 seconds. | M56: Recalling the handwashing sequence, including scrubbing for 10 to 15 seconds and drying with a single-use towel or hand dryer. | O56: Multiple choice (rewritten)
A57: AQ03-07 | B57: SSM9E Activity Quiz 3 | C57: Actions That Can Contaminate Food | D57: 3 | E57: The Safe Food Handler | F57: Work attire and personal behaviors | G57: Select all that apply | H57: Which of these actions can contaminate food? Select every one that applies. | I57: A. Touching your hair, face, or body B. Wearing a hat while prepping food C. Handling money D. Wearing a clean apron E. Sneezing, coughing, or using a tissue | J57: A, C, E: Touching your hair, face, or body; Handling money; Sneezing, coughing, or using a tissue | K57: Source | L57: Touching the body, handling money and sneezing or coughing all put pathogens on hands or food. | M57: Spotting personal behaviors that contaminate food: touching hair, face or body, handling money, and sneezing or coughing. A hat and a clean apron protect food. | O57: Multiple choice (rewritten)
A58: AQ03-08 | B58: SSM9E Activity Quiz 3 | C58: Exclude or Restrict? #1 | D58: 3 | E58: The Safe Food Handler | F58: Reporting illness, restricting and excluding | G58: Multiple choice | H58: A food handler at a hospital has a sore throat and a fever. Should the food handler be excluded or restricted? | I58: A. Exclude from the operation B. Restrict from working with or around food | J58: A. Exclude from the operation | K58: Source | L58: Sore throat with fever: restrict, but exclude if the operation primarily serves a high-risk population. | M58: Knowing that sore throat with fever means restrict, except in an operation serving a high-risk population (like a hospital), where it means exclude. | O58: Multiple choice
A59: AQ03-09 | B59: SSM9E Activity Quiz 3 | C59: Exclude or Restrict? #2 | D59: 3 | E59: The Safe Food Handler | F59: Reporting illness, restricting and excluding | G59: Multiple choice | H59: A food handler at a nursing home has jaundice from an infectious condition. Should the food handler be excluded or restricted? | I59: A. Exclude from the operation B. Restrict from working with or around food | J59: A. Exclude from the operation | K59: Source | L59: Food handlers with jaundice must be excluded and the regulatory authority notified. | M59: Knowing that jaundice is always an exclusion (and must be reported to the regulatory authority). | O59: Multiple choice
A60: AQ03-10 | B60: SSM9E Activity Quiz 3 | C60: Exclude or Restrict? #3 | D60: 3 | E60: The Safe Food Handler | F60: Reporting illness, restricting and excluding | G60: Multiple choice | H60: A food handler at a restaurant was vomiting this morning from an infectious condition. Should the food handler be excluded or restricted? | I60: A. Exclude from the operation B. Restrict from working with or around food | J60: A. Exclude from the operation | K60: Source | L60: Vomiting and diarrhea mean exclusion until symptom-free for 24 hours or cleared by a medical practitioner. | M60: Knowing that vomiting from an infectious condition means exclude, in any operation. | O60: Multiple choice
A61: AQ03-11 | B61: SSM9E Activity Quiz 3 | C61: Exclude or Restrict? #4 | D61: 3 | E61: The Safe Food Handler | F61: Reporting illness, restricting and excluding | G61: Multiple choice | H61: A food handler at a restaurant has been diagnosed with an illness caused by Salmonella Typhi. Should the food handler be excluded or restricted? | I61: A. Exclude from the operation B. Restrict from working with or around food | J61: A. Exclude from the operation | K61: Source | L61: A food handler diagnosed with Salmonella Typhi must be excluded and the illness reported to the regulatory authority. | M61: Knowing that a diagnosis with one of the Big Six pathogens, such as Salmonella Typhi, means exclude. | O61: Multiple choice
A62: AQ04-01 | B62: SSM9E Activity Quiz 4 | C62: True or False #1 | D62: 4 | E62: The Flow of Food: An Introduction | F62: Preventing cross-contamination | G62: True / false | H62: Rinsing a cutting board will prevent cross-contamination with the next food item placed on it. | I62: A. True B. False | J62: False | K62: Source | L62: Surfaces must be cleaned and sanitized between tasks; a rinse does not remove pathogens. | M62: Knowing that only cleaning and sanitizing a surface prevents cross-contamination; rinsing alone leaves pathogens behind. | O62: Multiple choice (rewritten)
A63: AQ04-02 | B63: SSM9E Activity Quiz 4 | C63: True or False #2 | D63: 4 | E63: The Flow of Food: An Introduction | F63: Thermometers and calibration | G63: True / false | H63: Some thermometers cannot be calibrated. | I63: A. True B. False | J63: True | K63: Source | L63: Some thermometers can’t be adjusted; follow the manufacturer’s directions to check their accuracy. | M63: Knowing that some thermometers (such as many digital ones) can’t be calibrated, so follow the manufacturer’s directions. | O63: Multiple choice (rewritten)
A64: AQ04-03 | B64: SSM9E Activity Quiz 4 | C64: True or False #3 | D64: 4 | E64: The Flow of Food: An Introduction | F64: Temperature danger zone and time-temperature abuse | G64: True / false | H64: Chicken held at an internal temperature of 125°F (52°C) has been time-temperature abused. | I64: A. True B. False | J64: True | K64: Source | L64: Hot TCS food must be held at 135°F (57°C) or higher; 125°F is inside the temperature danger zone. | M64: Applying the temperature danger zone: 125°F is between 41°F and 135°F, so hot-held chicken at that temperature has been abused. | O64: Multiple choice (rewritten)
A65: AQ04-04 | B65: SSM9E Activity Quiz 4 | C65: Cross-Contamination | D65: 4 | E65: The Flow of Food: An Introduction | F65: Preventing cross-contamination | G65: List | H65: Name two ways you can prevent cross-contamination. | J65: Any 2 of: Use separate equipment for raw and ready-to-eat food; Clean and sanitize all work surfaces, equipment and utensils before and after each task; Prep raw meat, fish and poultry and ready-to-eat food at different times; Buy prepared food | K65: Source | L65: Separating raw and ready-to-eat food by equipment or time, and cleaning and sanitizing between tasks, all prevent cross-contamination. | M65: Recalling practical ways to keep raw food away from ready-to-eat food: separate equipment, clean and sanitize between tasks, prep at different times, or buy prepared food. | O65: Knowledge point
A66: AQ04-05 | B66: SSM9E Activity Quiz 4 | C66: Temperature Danger Zone #1 | D66: 4 | E66: The Flow of Food: An Introduction | F66: Temperature danger zone and time-temperature abuse | G66: Fill in the blank | H66: The temperature danger zone is ____°F (____°C) to ____°F (____°C). | J66: 41°F (5°C) to 135°F (57°C) | K66: Source | L66: Pathogens grow between 41°F (5°C) and 135°F (57°C). | M66: Recalling the temperature danger zone range in both units. | O66: Multiple choice (rewritten)
A67: AQ04-06 | B67: SSM9E Activity Quiz 4 | C67: Temperature Danger Zone #2 | D67: 4 | E67: The Flow of Food: An Introduction | F67: Temperature danger zone and time-temperature abuse | G67: Fill in the blank | H67: Foodborne pathogens grow most quickly between ____°F (____°C) and ____°F (____°C). | J67: 70°F (21°C) to 125°F (52°C) | K67: Source | L67: Growth is fastest between 70°F (21°C) and 125°F (52°C). | M67: Recalling the narrower range of fastest growth inside the danger zone. Don’t mix it up with the full 41°F–135°F zone. | O67: Multiple choice (rewritten)
A68: AQ04-07 | B68: SSM9E Activity Quiz 4 | C68: General Thermometer Guidelines #1 | D68: 4 | E68: The Flow of Food: An Introduction | F68: Thermometers and calibration | G68: Fill in the blank | H68: Thermometers used to measure the temperature of food must be accurate to ____. | J68: +/- 2°F or +/- 1°C | K68: Source | L68: Food thermometers must be accurate to within ±2°F or ±1°C. | M68: Recalling the accuracy requirement for food thermometers. | O68: Multiple choice (rewritten)
A69: AQ04-08 | B69: SSM9E Activity Quiz 4 | C69: General Thermometer Guidelines #2 | D69: 4 | E69: The Flow of Food: An Introduction | F69: Thermometers and calibration | G69: Fill in the blank | H69: Place a probe into the ____ part of the food. | J69: thickest | K69: Source | L69: The thickest part of the food is usually the last to reach a safe temperature. | M69: Knowing where to take a food’s temperature: the thickest part, which heats and cools most slowly. | O69: Multiple choice (rewritten)
A70: AQ04-09 | B70: SSM9E Activity Quiz 4 | C70: General Thermometer Guidelines #3 | D70: 4 | E70: The Flow of Food: An Introduction | F70: Thermometers and calibration | G70: Fill in the blank | H70: Wait ____ seconds after inserting a bimetallic stemmed thermometer before recording the temperature of a food. | J70: 15 | K70: Source | L70: Wait at least 15 seconds after inserting the stem before reading it. | M70: Recalling how long a bimetallic stemmed thermometer needs to give a steady reading. | O70: Multiple choice (rewritten)
A71: AQ04-10 | B71: SSM9E Activity Quiz 4 | C71: General Thermometer Guidelines #4 | D71: 4 | E71: The Flow of Food: An Introduction | F71: Thermometers and calibration | G71: Fill in the blank | H71: Make sure your thermometers are accurate by ____ them regularly. | J71: calibrating | K71: Source | L71: Calibrate thermometers regularly, for example with the ice-point method. | M71: Knowing that calibration keeps thermometers accurate. | O71: Multiple choice (rewritten)
A72: AQ04-11 | B72: SSM9E Activity Quiz 4 | C72: General Thermometer Guidelines #5 | D72: 4 | E72: The Flow of Food: An Introduction | F72: Thermometers and calibration | G72: Fill in the blank | H72: Sanitize thermometers by using a sanitizing solution appropriate for ____ surfaces. | J72: food-contact | K72: Source | L72: Thermometer probes touch food, so use a sanitizer approved for food-contact surfaces. | M72: Knowing that a thermometer stem is a food-contact surface and must be cleaned and sanitized like one. | O72: Multiple choice (rewritten)
A73: AQ05-01 | B73: SSM9E Activity Quiz 5 | C73: True or False #1 | D73: 5 | E73: The Flow of Food: Purchasing, Receiving, and Storage | F73: Storage temperature, rotation and order | G73: True / false | H73: You can store food in any durable container that you can cover. | I73: A. True B. False | J73: False | K73: Source | L73: Store food in containers intended for food that are durable, leakproof and able to be sealed or covered. | M73: Knowing that storage containers must also be designed for food (food-grade) and leakproof; durable and covered isn’t enough. Watch for “any.” | O73: Multiple choice (rewritten)
A74: AQ05-02 | B74: SSM9E Activity Quiz 5 | C74: True or False #2 | D74: 5 | E74: The Flow of Food: Purchasing, Receiving, and Storage | F74: Storage temperature, rotation and order | G74: True / false | H74: Arrange stored food by its use-by date so that you use the oldest food first. | I74: A. True B. False | J74: True | K74: Source | L74: FIFO: store items with the earliest use-by or expiration dates in front of later ones and use them first. | M74: Knowing first-in, first-out (FIFO) rotation: earliest use-by dates go in front and get used first. | O74: Multiple choice (rewritten)
A75: AQ05-03 | B75: SSM9E Activity Quiz 5 | C75: True or False #3 | D75: 5 | E75: The Flow of Food: Purchasing, Receiving, and Storage | F75: Receiving temperatures | G75: True / false | H75: You should reject a delivery of frozen steaks covered in ice crystals. | I75: A. True B. False | J75: True | K75: Source | L75: Frozen food with large ice crystals or frozen liquids has been thawed and refrozen and must be rejected. | M75: Recognizing ice crystals on frozen food as a sign it thawed and was refrozen (time-temperature abuse), so it must be rejected. | O75: Multiple choice (rewritten)
A76: AQ05-04 | B76: SSM9E Activity Quiz 5 | C76: True or False #4 | D76: 5 | E76: The Flow of Food: Purchasing, Receiving, and Storage | F76: Storage temperature, rotation and order | G76: True / false | H76: Unwashed produce must be separated from ready-to-eat food. | I76: A. True B. False | J76: True | K76: Source | L76: Dirt and pathogens on unwashed produce can contaminate ready-to-eat food. | M76: Knowing that unwashed produce can carry pathogens to ready-to-eat food and must be stored away from it. | O76: Multiple choice (rewritten)
A77: AQ05-05 | B77: SSM9E Activity Quiz 5 | C77: Complete the Label | D77: 5 | E77: The Flow of Food: Purchasing, Receiving, and Storage | F77: Labeling and date marking | G77: Fill in the blank | H77: On Sunday, 8/3, you prepped melon balls at 2:00 p.m. You used some for a fruit salad and stored the rest. Complete the “USE BY” label for the food you stored: Date ____; time ____ (a.m. or p.m.); food name ____. | J77: 8/9; 2:00 p.m.; Melon balls | K77: Source | L77: Cut melon is a ready-to-eat TCS food; label it with its name and a use-by date 7 days out, counting the prep day as day 1. | M77: Applying date marking: ready-to-eat TCS food prepped on-site can be kept 7 days at 41°F or lower, and the prep day counts as day 1, so 8/3 becomes 8/9. | N77: The original shows a blank label to fill in; the answer key shows the completed label as a picture. | O77: Multiple choice (rewritten)
A78: AQ05-06 | B78: SSM9E Activity Quiz 5 | C78: Fill in the Blank #1 | D78: 5 | E78: The Flow of Food: Purchasing, Receiving, and Storage | F78: Storage temperature, rotation and order | G78: Fill in the blank | H78: Store food at least ____ inch(es) [____ centimeter(s)] off the floor. | J78: six; fifteen | K78: Source | L78: Store food away from walls and at least 6 inches (15 centimeters) off the floor. | M78: Recalling the storage height rule: 6 inches (15 cm) off the floor, which also applies to stationary equipment on legs. | O78: Multiple choice (rewritten)
A79: AQ05-07 | B79: SSM9E Activity Quiz 5 | C79: Fill in the Blank #2 | D79: 5 | E79: The Flow of Food: Purchasing, Receiving, and Storage | F79: Storage temperature, rotation and order | G79: Fill in the blank | H79: Store raw meat, poultry, and seafood ____ ready-to-eat food. | J79: below | K79: Source | L79: Raw meat, poultry and seafood go below ready-to-eat food (or in separate coolers). | M79: Knowing the top-to-bottom storage rule: raw meat, poultry and seafood go below ready-to-eat food so drips can’t contaminate it. | O79: Multiple choice (rewritten)
A80: AQ05-08 | B80: SSM9E Activity Quiz 5 | C80: Fill in the Blank #3 | D80: 5 | E80: The Flow of Food: Purchasing, Receiving, and Storage | F80: Approved suppliers and recalls | G80: Fill in the blank | H80: Purchase food from ____, reputable suppliers. | J80: approved | K80: Source | L80: Approved suppliers have been inspected and meet all applicable local, state and federal laws. | M80: Knowing that all food must come from approved, reputable suppliers that meet applicable laws. | O80: Multiple choice (rewritten)
A81: AQ05-09 | B81: SSM9E Activity Quiz 5 | C81: Fill in the Blank #4 | D81: 5 | E81: The Flow of Food: Purchasing, Receiving, and Storage | F81: Labeling and date marking | G81: Fill in the blank | H81: Store ready-to-eat TCS food that is prepared on-site for no more than ____ days. | J81: seven | K81: Source | L81: Ready-to-eat TCS food prepped on-site can be stored for up to 7 days at 41°F (5°C) or lower. | M81: Recalling the date-marking limit: 7 days at 41°F (5°C) or lower for ready-to-eat TCS food prepped on-site. | O81: Multiple choice (rewritten)
A82: AQ05-10 | B82: SSM9E Activity Quiz 5 | C82: Store the Food #1 | D82: 5 | E82: The Flow of Food: Purchasing, Receiving, and Storage | F82: Storage temperature, rotation and order | G82: Multiple choice | H82: A cooler has three shelves: A (top), B (middle) and C (bottom). Raw poultry, ground beef and a cake must all be stored in it. Which shelf should the raw poultry go on? | I82: A. Shelf A (top) B. Shelf B (middle) C. Shelf C (bottom) | J82: C. Shelf C (bottom) | K82: Source | L82: Store food by minimum internal cooking temperature, highest at the bottom: poultry goes on the lowest shelf. | M82: Applying storage order by minimum cooking temperature: poultry (165°F) goes lowest, below ground meat and ready-to-eat food. | N82: The original shows a picture of the cooler. | O82: Multiple choice
A83: AQ05-11 | B83: SSM9E Activity Quiz 5 | C83: Store the Food #2 | D83: 5 | E83: The Flow of Food: Purchasing, Receiving, and Storage | F83: Storage temperature, rotation and order | G83: Multiple choice | H83: A cooler has three shelves: A (top), B (middle) and C (bottom). Raw poultry, ground beef and a cake must all be stored in it. Which shelf should the ground beef go on? | I83: A. Shelf A (top) B. Shelf B (middle) C. Shelf C (bottom) | J83: B. Shelf B (middle) | K83: Source | L83: Ground meat goes above poultry and below ready-to-eat food. | M83: Applying storage order: ground beef (155°F) goes above poultry (165°F) but below ready-to-eat food. | N83: The original shows a picture of the cooler. | O83: Multiple choice
A84: AQ05-12 | B84: SSM9E Activity Quiz 5 | C84: Store the Food #3 | D84: 5 | E84: The Flow of Food: Purchasing, Receiving, and Storage | F84: Storage temperature, rotation and order | G84: Multiple choice | H84: A cooler has three shelves: A (top), B (middle) and C (bottom). Raw poultry, ground beef and a cake must all be stored in it. Which shelf should the cake go on? | I84: A. Shelf A (top) B. Shelf B (middle) C. Shelf C (bottom) | J84: A. Shelf A (top) | K84: Source | L84: Ready-to-eat food goes on the top shelf so nothing raw can drip onto it. | M84: Applying storage order: ready-to-eat food such as cake goes on the top shelf, above all raw meat. | N84: The original shows a picture of the cooler. | O84: Multiple choice
A85: AQ06-01 | B85: SSM9E Activity Quiz 6 | C85: True or False #1 | D85: 6 | E85: The Flow of Food: Preparation | F85: Cooling and reheating | G85: True / false | H85: Coolers are designed to cool hot food quickly. | I85: A. True B. False | J85: False | K85: Source | L85: Coolers keep cold food cold; hot food placed in them cools too slowly and can warm the food around it. | M85: Knowing that coolers are built to keep cold food cold, not to cool hot food, so other cooling methods are needed. | O85: Multiple choice (rewritten)
A86: AQ06-02 | B86: SSM9E Activity Quiz 6 | C86: True or False #2 | D86: 6 | E86: The Flow of Food: Preparation | F86: Minimum internal cooking temperatures | G86: True / false | H86: Cook a whole turkey to a minimum internal cooking temperature of 155°F (68°C) for 17 seconds. | I86: A. True B. False | J86: False | K86: Source | L86: Poultry must be cooked to 165°F (74°C) for <1 second. | M86: Recalling that all poultry, whole or ground, must reach 165°F (74°C) for <1 second. 155°F for 17 seconds is the ground-meat temperature. | O86: Multiple choice (rewritten)
A87: AQ06-03 | B87: SSM9E Activity Quiz 6 | C87: True or False #3 | D87: 6 | E87: The Flow of Food: Preparation | F87: Cooling and reheating | G87: True / false | H87: The first step in cooling TCS food is to cool it from 135°F to 70°F (57°C to 21°C) within four hours. | I87: A. True B. False | J87: False | K87: Source | L87: Stage 1 is 135°F to 70°F within two hours; stage 2 is 70°F to 41°F within the next four hours. | M87: Recalling two-stage cooling: 135°F to 70°F within 2 hours, then 70°F to 41°F within the next 4 hours. The trap swaps the two time limits. | O87: Multiple choice (rewritten)
A88: AQ06-04 | B88: SSM9E Activity Quiz 6 | C88: True or False #4 | D88: 6 | E88: The Flow of Food: Preparation | F88: Minimum internal cooking temperatures | G88: True / false | H88: Fish cooked in a microwave must be cooked to a minimum internal temperature of 145°F (63°C). | I88: A. True B. False | J88: False | K88: Source | L88: Microwave-cooked meat, seafood, poultry and eggs must reach 165°F (74°C), then stand 2 minutes covered. | M88: Knowing the microwave rule: meat, seafood, poultry and eggs cooked in a microwave must reach 165°F (74°C). 145°F is for fish cooked other ways. | O88: Multiple choice (rewritten)
A89: AQ06-05 | B89: SSM9E Activity Quiz 6 | C89: True or False #5 | D89: 6 | E89: The Flow of Food: Preparation | F89: Prepping specific foods and variances | G89: True / false | H89: Unwashed produce must be separated from ready-to-eat foods. | I89: A. True B. False | J89: True | K89: Source | L89: Pathogens on unwashed produce can spread to ready-to-eat food. | M89: Knowing that unwashed produce can contaminate ready-to-eat food during prep and storage. | O89: Multiple choice (rewritten)
A90: AQ06-06 | B90: SSM9E Activity Quiz 6 | C90: Methods of Thawing | D90: 6 | E90: The Flow of Food: Preparation | F90: Thawing | G90: List | H90: What are the four acceptable methods of thawing food? | J90: In the cooler (at 41°F/5°C or lower); Submerged under running drinkable water at 70°F (21°C) or lower; In a microwave (if cooked immediately afterward); As part of the cooking process | K90: Source | L90: Food must be thawed in ways that keep it out of the temperature danger zone. | M90: Recalling the four safe thawing methods. Thawing at room temperature is never acceptable. | O90: Knowledge point
A91: AQ06-07 | B91: SSM9E Activity Quiz 6 | C91: Minimum Internal Cooking Temperatures #1 | D91: 6 | E91: The Flow of Food: Preparation | F91: Minimum internal cooking temperatures | G91: Multiple choice | H91: What is the minimum internal cooking temperature for swordfish steaks? | I91: A. 165°F (74°C) for <1 second B. 155°F (68°C) for 17 seconds C. 145°F (63°C) for 15 seconds D. 145°F (63°C) for 4 minutes E. 135°F (57°C) | J91: C. 145°F (63°C) for 15 seconds | K91: Source | L91: Seafood, including fish such as swordfish, must reach 145°F (63°C) for 15 seconds. | M91: Recalling that seafood (fish steaks and fillets) is cooked to 145°F (63°C) for 15 seconds. | O91: Multiple choice
A92: AQ06-08 | B92: SSM9E Activity Quiz 6 | C92: Minimum Internal Cooking Temperatures #2 | D92: 6 | E92: The Flow of Food: Preparation | F92: Minimum internal cooking temperatures | G92: Multiple choice | H92: What is the minimum internal cooking temperature for a whole chicken? | I92: A. 165°F (74°C) for <1 second B. 155°F (68°C) for 17 seconds C. 145°F (63°C) for 15 seconds D. 145°F (63°C) for 4 minutes E. 135°F (57°C) | J92: A. 165°F (74°C) for <1 second | K92: Source | L92: Poultry (whole or ground chicken, turkey, duck) must reach 165°F (74°C) for <1 second. | M92: Recalling that all poultry is cooked to 165°F (74°C) for <1 second. | O92: Multiple choice
A93: AQ06-09 | B93: SSM9E Activity Quiz 6 | C93: Minimum Internal Cooking Temperatures #3 | D93: 6 | E93: The Flow of Food: Preparation | F93: Minimum internal cooking temperatures | G93: Multiple choice | H93: What is the minimum internal cooking temperature for pork chops? | I93: A. 165°F (74°C) for <1 second B. 155°F (68°C) for 17 seconds C. 145°F (63°C) for 15 seconds D. 145°F (63°C) for 4 minutes E. 135°F (57°C) | J93: C. 145°F (63°C) for 15 seconds | K93: Source | L93: Pork chops are whole-muscle steaks/chops: 145°F (63°C) for 15 seconds. | M93: Recalling that steaks and chops of pork, beef, veal and lamb are cooked to 145°F (63°C) for 15 seconds. 4 minutes is for roasts. | O93: Multiple choice
A94: AQ06-10 | B94: SSM9E Activity Quiz 6 | C94: Minimum Internal Cooking Temperatures #4 | D94: 6 | E94: The Flow of Food: Preparation | F94: Minimum internal cooking temperatures | G94: Multiple choice | H94: What is the minimum internal cooking temperature for ground-beef patties? | I94: A. 165°F (74°C) for <1 second B. 155°F (68°C) for 17 seconds C. 145°F (63°C) for 15 seconds D. 145°F (63°C) for 4 minutes E. 135°F (57°C) | J94: B. 155°F (68°C) for 17 seconds | K94: Source | L94: Ground meat (beef, pork, other meat) must reach 155°F (68°C) for 17 seconds. | M94: Recalling that ground meat is cooked to 155°F (68°C) for 17 seconds because grinding spreads surface pathogens through the meat. | O94: Multiple choice
A95: AQ06-11 | B95: SSM9E Activity Quiz 6 | C95: Minimum Internal Cooking Temperatures #5 | D95: 6 | E95: The Flow of Food: Preparation | F95: Minimum internal cooking temperatures | G95: Multiple choice | H95: What is the minimum internal cooking temperature for glazed carrots that will be hot-held? | I95: A. 165°F (74°C) for <1 second B. 155°F (68°C) for 17 seconds C. 145°F (63°C) for 15 seconds D. 145°F (63°C) for 4 minutes E. 135°F (57°C) | J95: E. 135°F (57°C) | K95: Source | L95: Plant foods cooked for hot holding must reach 135°F (57°C). | M95: Recalling that fruit, vegetables, grains and legumes cooked for hot holding need 135°F (57°C). | O95: Multiple choice
A96: AQ06-12 | B96: SSM9E Activity Quiz 6 | C96: Cooling Food | D96: 6 | E96: The Flow of Food: Preparation | F96: Cooling and reheating | G96: Short answer | H96: What is one way you can correctly cool a large pot of chili? | J96: Divide it into smaller containers, then cool it with one of these: place it in an ice-water bath and stir it; stir it with ice paddles; or put it in a blast chiller. The chili could also be made with less water, and cold water or ice added after cooking. | K96: Source | L96: Large amounts of food cool too slowly; dividing them and using an active cooling method gets them through the danger zone in time. | M96: Applying cooling methods: first divide the food into smaller containers, then use an ice-water bath, ice paddles, a blast chiller, or add ice or cold water to a reduced-water recipe. | O96: Knowledge point
A97: AQ07-01 | B97: SSM9E Activity Quiz 7 | C97: True or False #1 | D97: 7 | E97: The Flow of Food: Service | F97: Holding food and time as a control | G97: True / false | H97: Hold cold TCS food at an internal temperature of 41°F (5°C) or lower. | I97: A. True B. False | J97: True | K97: Source | L97: Cold TCS food must be held at 41°F (5°C) or lower. | M97: Recalling the cold-holding temperature. | O97: Multiple choice (rewritten)
A98: AQ07-02 | B98: SSM9E Activity Quiz 7 | C98: True or False #2 | D98: 7 | E98: The Flow of Food: Service | F98: Holding food and time as a control | G98: True / false | H98: Hold hot TCS food at an internal temperature of 120°F (49°C) or higher. | I98: A. True B. False | J98: False | K98: Source | L98: Hot TCS food must be held at 135°F (57°C) or higher. | M98: Recalling the hot-holding temperature, 135°F (57°C); 120°F is inside the temperature danger zone. | O98: Multiple choice (rewritten)
A99: AQ07-03 | B99: SSM9E Activity Quiz 7 | C99: True or False #3 | D99: 7 | E99: The Flow of Food: Service | F99: Holding food and time as a control | G99: True / false | H99: Your operation may be allowed to hold chicken salad without temperature control if the operation has written procedures maintained on-site and made available to the regulatory authority upon request. | I99: A. True B. False | J99: True | K99: Source | L99: Holding food without temperature control requires written procedures available to the regulatory authority. | M99: Knowing that time can be used as a control for TCS food only with written procedures kept on-site and approved by the regulatory authority if required. | O99: Multiple choice (rewritten)
A100: AQ07-04 | B100: SSM9E Activity Quiz 7 | C100: True or False #4 | D100: 7 | E100: The Flow of Food: Service | F100: Holding food and time as a control | G100: True / false | H100: When holding TCS food for service, the internal temperature must be checked at least every four hours. | I100: A. True B. False | J100: True | K100: Source | L100: Check held food at least every four hours; checking every two hours leaves time to fix problems. | M100: Recalling how often to check held food: at least every four hours (every two hours leaves time for corrective action). | O100: Multiple choice (rewritten)
A101: AQ07-05 | B101: SSM9E Activity Quiz 7 | C101: True or False #5 | D101: 7 | E101: The Flow of Food: Service | F101: Serving food safely | G101: True / false | H101: A serving utensil cannot be stored outside of the food. | I101: A. True B. False | J101: False | K101: Source | L101: Serving utensils can be stored in the food with the handle extended above the rim, or on a clean and sanitized food-contact surface. | M101: Knowing the acceptable places for serving utensils: in the food with the handle out, or on a clean and sanitized food-contact surface. | O101: Multiple choice (rewritten)
A102: AQ07-06 | B102: SSM9E Activity Quiz 7 | C102: True or False #6 | D102: 7 | E102: The Flow of Food: Service | F102: Serving food safely | G102: True / false | H102: A single-service carryout container cannot be refilled for a customer. | I102: A. True B. False | J102: True | K102: Source | L102: Single-service containers are not designed to be cleaned and sanitized, so they must not be refilled. | M102: Knowing that single-service items are designed to be used once and can’t be safely cleaned and reused. | O102: Multiple choice (rewritten)
A103: AQ07-07 | B103: SSM9E Activity Quiz 7 | C103: Service Guidelines #1 | D103: 7 | E103: The Flow of Food: Service | F103: Serving food safely | G103: Short answer | H103: A server puts ice into a glass with their bare hands. What is the server doing wrong, and what should they do instead? | J103: The server is using their hands to put ice into a glass. The server should use an ice scoop or tongs. | K103: Source | L103: Ice is a ready-to-eat food; bare hands can contaminate it. | M103: Recognizing that ice is a ready-to-eat food and must never be handled with bare hands; use an ice scoop or tongs. | N103: The original shows a picture; the question is written from the answer key’s description of it. | O103: Knowledge point
A104: AQ07-08 | B104: SSM9E Activity Quiz 7 | C104: Service Guidelines #2 | D104: 7 | E104: The Flow of Food: Service | F104: Serving food safely | G104: Short answer | H104: A server holds a serving spoon by the bowl, the part that touches food. What is the server doing wrong, and what should they do instead? | J104: The server is holding the spoon by the food-contact surface. The server should hold the spoon by the handle. | K104: Source | L104: Touching the food-contact surface of a utensil can transfer pathogens to the food. | M104: Knowing to hold serving utensils by the handle so hands never touch food-contact surfaces. | N104: The original shows a picture; the question is written from the answer key’s description of it. | O104: Knowledge point
...

Sheet Assigned answers
A1: ID | B1: Source | C1: Where in source | D1: Chapter | E1: Chapter name | F1: Topic | G1: Question type | H1: Question | I1: Answer choices | J1: Correct answer | K1: Answer from | L1: Explanation | M1: What it tests | N1: Note | O1: On the website as
A2: MT-09 | B2: Mock ServSafe Test | C2: Q9 | D2: 1 | E2: Providing Safe Food | F2: Manager role, training and inspections | G2: Multiple choice | H2: A manager can ensure employees are following their training by | I2: A. reviewing the most current regulatory inspection report. B. having them complete a written assessment. C. asking them if they can do what they were trained to do. D. monitoring them. | J2: D. monitoring them. | K2: Assigned (high confidence) | L2: Managers make sure training is followed by monitoring employees. DT-11 asks the same question and its key answer is “monitoring them.” | M2: Knowing that monitoring confirms employees follow their training. Asking them or giving a written test only checks what they say or know, not what they do. | N2: Same question as DT-11. | O2: Multiple choice
A3: MT-21 | B3: Mock ServSafe Test | C3: Q21 | D3: 2 | E3: Forms of Contamination | F3: Big Six pathogens and linked foods | G3: Multiple choice | H3: Unpasteurized dairy products are commonly linked with what type of food? | I3: A. Listeria B. Bacillus cereus C. Salmonella Typhi D. Vibrio vulnificus | J3: A. Listeria | K3: Assigned (high confidence) | L3: Listeria monocytogenes is linked with unpasteurized dairy products, raw meat and ready-to-eat deli food. | M3: Linking pathogens to foods: Listeria with unpasteurized dairy. Bacillus cereus is best known for cooked rice dishes, Salmonella Typhi for ready-to-eat food and beverages, and Vibrio vulnificus for raw oysters. | N3: The question says “what type of food” but means which pathogen; all four options are pathogens. | O3: Multiple choice
A4: MT-22 | B4: Mock ServSafe Test | C4: Q22 | D4: 6 | E4: The Flow of Food: Preparation | F4: Cooling and reheating | G4: Multiple choice | H4: Which TCS food is being cooled correctly? | I4: A. Chicken pot pie is placed in a freezer. B. A beef roast is loosely covered and placed on the top shelf in the cooler. C. Minestrone soup is stirred with an ice paddle D. A tofu stir fry is covered tightly and placed outside in the winter. | J4: C. Minestrone soup is stirred with an ice paddle | K4: Assigned (high confidence) | L4: Stirring with an ice paddle is an approved cooling method. Freezers and coolers are not designed to cool hot food quickly, and leaving food outside is not controlled cooling. | M4: Knowing the approved cooling methods: ice-water bath, ice paddle, blast chiller, or adding ice as an ingredient. Putting hot food in a freezer or cooler alone is the trap. | O4: Multiple choice
A5: MT-25 | B5: Mock ServSafe Test | C5: Q25 | D5: 8 | E5: Food Safety Management Systems | F5: Food safety culture and active managerial control | G5: Multiple choice | H5: Three components of active managerial control include | I5: A. identifying risks, record keeping, and training. B. identifying risks, creating purchase orders, and training. C. identifying risks, creating specifications, and training. D. identifying risks, corrective action, and training. | J5: D. identifying risks, corrective action, and training. | K5: Assigned (high confidence) | L5: The six steps of active managerial control are identifying risks, monitoring, corrective action, management oversight, training and re-evaluation. Record keeping, purchase orders and specifications are not among them. | M5: Recalling the steps of active managerial control. Record keeping is a HACCP principle, and purchase orders or specifications are purchasing tasks. | O5: Multiple choice
A6: MT-33 | B6: Mock ServSafe Test | C6: Q33 | D6: 9 | E6: Safe Facilities and Pest Management | F6: Lighting, ventilation, garbage and wastewater | G6: Multiple choice | H6: Outdoor garbage containers must be | I6: A. washed frequently. B. kept away from customer parking areas. C. lined with plastic or wet-strength paper. D. kept covered with tight-fitting lids. | J6: D. kept covered with tight-fitting lids. | K6: Assigned (high confidence) | L6: Outdoor garbage containers must have tight-fitting lids and be kept covered. DT-74 asks the same thing and its key is “kept covered at all times.” | M6: Recalling the rules for outdoor garbage containers: tight-fitting lids, kept covered, on a smooth, durable surface. Distance from customer parking is not a requirement. | N6: Similar to DT-74. | O6: Multiple choice
A7: MT-34 | B7: Mock ServSafe Test | C7: Q34 | D7: 2 | E7: Forms of Contamination | F7: Viruses, parasites, fungi and biological toxins | G7: Multiple choice | H7: Domoic acid is a toxin found in shellfish from the Pacific Northwest and causes which illness? | I7: A. Ciguatera fish poisoning B. Amnesic shellfish poisoning (ASP) C. Scrombroid poisoning D. Paralytic shellfish poisoning (PSP) | J7: B. Amnesic shellfish poisoning (ASP) | K7: Assigned (high confidence) | L7: Domoic acid causes amnesic shellfish poisoning (ASP). Paralytic shellfish poisoning (PSP) is caused by a different toxin (saxitoxin). | M7: Matching shellfish toxins to illnesses: domoic acid causes amnesic shellfish poisoning. PSP is the close look-alike; ciguatera and scombroid poisoning come from finfish. | O7: Multiple choice
A8: MT-38 | B8: Mock ServSafe Test | C8: Q38 | D8: 5 | E8: The Flow of Food: Purchasing, Receiving, and Storage | F8: Receiving: packaging, documents and quality | G8: Multiple choice | H8: How long must shellstock tags be kept on file? | I8: A. 90 days after the last shellfish was sold or served from the container B. 30 days after the last shellfish was sold or served from the container C. 30 days after the day the shellfish were received | J8: A. 90 days after the last shellfish was sold or served from the container | K8: Assigned (high confidence) | L8: Shellstock tags must be kept for 90 days from the date the last shellfish was sold or served from the container. PT-38 also keys 90 days. | M8: Recalling both parts of the tag rule: 90 days, counted from when the last shellfish in the container was used, not from receiving. | N8: Similar to PT-38. | O8: Multiple choice
A9: MT-42 | B9: Mock ServSafe Test | C9: Q42 | D9: 7 | E9: The Flow of Food: Service | F9: Serving food safely | G9: Multiple choice | H9: A customer returns a carryout container to a restaurant to be refilled with food. It looks clean, but they will not refill it. Is the restaurant correct to refuse? | I9: A. No, because the container was made to hold food. B. No, because the container can be refilled for personal consumption. C. Yes, because the container is a single-service container that is not designed to be refilled. D. Yes, because the container may not have been appropriately cleaned and sanitized. | J9: C. Yes, because the container is a single-service container that is not designed to be refilled. | K9: Assigned (high confidence) | L9: Single-service containers are not designed to be reused, so they cannot be refilled. DT-09 asks the same question and its key is the single-service answer. | M9: Knowing single-service containers can never be refilled, however clean they look. The trap gives a sensible-sounding reason (it may not be sanitized) that isn’t the rule. | N9: Same question as DT-09. | O9: Multiple choice
A10: MT-46 | B10: Mock ServSafe Test | C10: Q46 | D10: 6 | E10: The Flow of Food: Preparation | F10: Minimum internal cooking temperatures | G10: Multiple choice | H10: A lamb roast must be cooked to an internal temperature of | I10: A. 145°F (63°C) for 4 minutes B. 155°F (68°C) for 17 seconds C. 145°F (63°C) for 15 seconds D. 135°F (57°C) with no minimum time | J10: A. 145°F (63°C) for 4 minutes | K10: Assigned (high confidence) | L10: Roasts of beef, pork, veal and lamb must be cooked to 145°F (63°C) for 4 minutes. | M10: Separating roasts (145°F for 4 minutes) from steaks and chops (145°F for 15 seconds), which is the trap the test-taker fell for. | O10: Multiple choice
A11: MT-48 | B11: Mock ServSafe Test | C11: Q48 | D11: 6 | E11: The Flow of Food: Preparation | F11: Cooling and reheating | G11: Multiple choice | H11: Which TCS food has been cooled correctly? | I11: A. Barbeque jackfruit cooled from 135°F to 70°F (57°C to 21°C) in three hours and then from 70°F to 41°F (21°C to 5°C) in two hours B. Corn chowder cooled from 135°F to 70°F (57°C to 21°C) in one hour and then from 70°F to 41°F (21°C to 5°C) in five hours C. Beef brisket cooled from 135°F to 70°F (57°C to 21°C) in two hours and then from 70°F to 41°F (21°C to 5°C) in six hours D. Oyster stuffing cooled from 135°F to 70°F (57°C to 21°C) in one hour and then from 70°F to 41°F (21°C to 5°C) in four hours | J11: B. Corn chowder cooled from 135°F to 70°F (57°C to 21°C) in one hour and then from 70°F to 41°F (21°C to 5°C) in five hours | K11: Assigned (medium confidence) | L11: Two-stage cooling allows 2 hours to reach 70°F (21°C) and 6 hours in total. The corn chowder took 1 hour, then 5 hours: 6 hours in total. | M11: Applying two-stage cooling: 2 hours or less to reach 70°F, 6 hours or less in total. When the first stage finishes early, the leftover time carries into the second stage. | N11: As written, option D (1 hour, then 4 hours) also meets the rule. The attempt marked D wrong, so the quiz’s intended answer is B, which uses the full 6 hours. | O11: Multiple choice
A12: RD-004 | B12: Review Slide Deck | C12: Slide 4 | D12: 1 | E12: Providing Safe Food | F12: How food becomes unsafe | G12: Multiple choice | H12: What is the problem shown in the picture? (The slide’s picture isn’t in the file.) | I12: A. Time-temperature abuse B. Cross-contamination C. Poor personal hygiene D. Poor cleaning and sanitizing | J12: Can’t be determined: the slide’s picture isn’t in the file | K12: Not answerable (picture missing) | L12: The four practices that make food unsafe are time-temperature abuse, cross-contamination, poor personal hygiene, and poor cleaning and sanitizing; which one applies depends on the picture. | M12: Recognizing which of the four practices that make food unsafe is happening in a situation. | O12: Not on the website (picture missing)
A13: RD-005 | B13: Review Slide Deck | C13: Slide 5 | D13: 1 | E13: Providing Safe Food | F13: How food becomes unsafe | G13: Multiple choice | H13: What is the problem shown in the picture? (The slide’s picture isn’t in the file.) | I13: A. Time-temperature abuse B. Cross-contamination C. Poor personal hygiene D. Poor cleaning and sanitizing | J13: Can’t be determined: the slide’s picture isn’t in the file | K13: Not answerable (picture missing) | L13: The four practices that make food unsafe are time-temperature abuse, cross-contamination, poor personal hygiene, and poor cleaning and sanitizing; which one applies depends on the picture. | M13: Recognizing which of the four practices that make food unsafe is happening in a situation. | O13: Not on the website (picture missing)
A14: RD-006 | B14: Review Slide Deck | C14: Slide 6 | D14: 1 | E14: Providing Safe Food | F14: How food becomes unsafe | G14: Multiple choice | H14: Between uses, a food handler just wipes the prep table with a single-use towel. What is the problem? | I14: A. Time-temperature abuse B. Cross-contamination C. Poor personal hygiene D. Poor cleaning and sanitizing | J14: D. Poor cleaning and sanitizing | K14: Assigned (medium confidence) | L14: Wiping is not cleaning and sanitizing: a food-contact surface must be cleaned, rinsed, and sanitized between uses, so this is poor cleaning and sanitizing. | M14: Telling poor cleaning and sanitizing apart from cross-contamination: the fault here is the missing clean-and-sanitize step, not raw food touching ready-to-eat food. | O14: Multiple choice
A15: RD-007 | B15: Review Slide Deck | C15: Slide 7 | D15: 1 | E15: Providing Safe Food | F15: TCS and ready-to-eat food | G15: Multiple choice | H15: Does cut lettuce need time and temperature control to keep it safe? | I15: A. Yes B. No | J15: A. Yes | K15: Assigned (high confidence) | L15: Cut leafy greens are TCS food and must be held at 41°F (5°C) or lower. | M15: Knowing that cutting changes some produce into TCS food: whole lettuce doesn’t need temperature control, but cut leafy greens do. | O15: Multiple choice
A16: RD-022 | B16: Review Slide Deck | C16: Slide 22 | D16: 2 | E16: Forms of Contamination | F16: Viruses, parasites, fungi and biological toxins | G16: Multiple choice | H16: What is the onset time for an illness from a biological toxin? | I16: A. Within a few minutes B. Within a few hours C. 6–12 hours D. 24 hours | J16: A. Within a few minutes | K16: Assigned (medium confidence) | L16: Illness from biological toxins (such as seafood toxins) usually starts within minutes of eating the food, though it varies by toxin. | M16: Knowing that toxin illnesses start fast, usually within minutes, unlike many bacterial and viral illnesses that take hours or days. | O16: Multiple choice
A17: RD-023 | B17: Review Slide Deck | C17: Slide 23 | D17: 2 | E17: Forms of Contamination | F17: Viruses, parasites, fungi and biological toxins | G17: Select all that apply | H17: Which symptoms are associated with illness from a biological toxin? Select all that apply. | I17: A. Vomiting and diarrhea B. Neurological symptoms C. Flushing, hives, and difficulty breathing D. Heart palpitations | J17: A, B, C, D: Vomiting and diarrhea; Neurological symptoms; Flushing, hives, and difficulty breathing; Heart palpitations | K17: Assigned (medium confidence) | L17: Depending on the toxin, symptoms can include vomiting or diarrhea, neurological symptoms (such as tingling), flushing, hives, difficulty breathing, and heart palpitations. | M17: Knowing the range of toxin symptoms, especially the neurological ones and flushing or hives, which aren’t typical of other foodborne illnesses. | N17: The slide lists the options without saying which are correct; all four are recognized symptoms. | O17: Multiple choice (rewritten)
A18: RD-029 | B18: Review Slide Deck | C18: Slide 29 | D18: 3 | E18: The Safe Food Handler | F18: Handwashing and hand care | G18: Multiple choice | H18: What should the temperature of the water be when you first wet your hands and when you rinse the soap off? | I18: A. Cold B. Warm C. As cold as you can stand D. As hot as you can stand | J18: B. Warm | K18: Assigned (high confidence) | L18: ServSafe’s handwashing steps (9th edition) say to wet and rinse hands and arms with warm running water. | M18: Recalling the handwashing steps: warm running water to wet and rinse, not the extremes. | O18: Multiple choice
A19: RD-037 | B19: Review Slide Deck | C19: Slide 37 | D19: 3 | E19: The Safe Food Handler | F19: Reporting illness, restricting and excluding | G19: Multiple choice | H19: Does a chef need to tell you if they have been diagnosed with an illness from Shigella spp.? | I19: A. Yes B. No | J19: A. Yes | K19: Assigned (high confidence) | L19: Food handlers must report a diagnosis of an illness caused by any of the Big Six pathogens, including Shigella spp., to the manager. | M19: Knowing that a Big Six diagnosis must always be reported to the manager. | O19: Multiple choice
A20: RD-038 | B20: Review Slide Deck | C20: Slide 38 | D20: 3 | E20: The Safe Food Handler | F20: Reporting illness, restricting and excluding | G20: Multiple choice | H20: Does a cook need to tell you if they live with someone diagnosed with hepatitis A? | I20: A. Yes B. No | J20: A. Yes | K20: Assigned (high confidence) | L20: Food handlers must tell the manager if they have been exposed to, or live with someone diagnosed with, an illness caused by a Big Six pathogen such as hepatitis A. | M20: Knowing that exposure counts too: living with someone diagnosed with a Big Six illness must be reported, even if the cook feels fine. | O20: Multiple choice
A21: RD-039 | B21: Review Slide Deck | C21: Slide 39 | D21: 3 | E21: The Safe Food Handler | F21: Reporting illness, restricting and excluding | G21: Multiple choice | H21: Do you have to report a food handler diagnosed with norovirus to the health department? | I21: A. Yes B. No | J21: A. Yes | K21: Assigned (high confidence) | L21: Managers must notify the regulatory authority when a food handler is diagnosed with an illness caused by a Big Six pathogen, such as norovirus. | M21: Knowing which cases go beyond the manager to the regulatory authority: Big Six diagnoses (and jaundice) must be reported. | O21: Multiple choice
A22: RD-041 | B22: Review Slide Deck | C22: Slide 41 | D22: 3 | E22: The Safe Food Handler | F22: Reporting illness, restricting and excluding | G22: Multiple choice | H22: A food handler has an infected wound that is not covered properly. Restrict or exclude? | I22: A. Restrict from working with exposed food, utensils, and equipment B. Exclude from the operation | J22: A. Restrict from working with exposed food, utensils, and equipment | K22: Assigned (high confidence) | L22: A food handler with an infected wound or boil that isn’t properly covered must be restricted from working with exposed food, utensils, and equipment. | M22: Knowing that an uncovered infected wound calls for restriction (keep away from food), not exclusion from the operation. | O22: Multiple choice
A23: RD-042 | B23: Review Slide Deck | C23: Slide 42 | D23: 3 | E23: The Safe Food Handler | F23: Reporting illness, restricting and excluding | G23: Multiple choice | H23: A food handler at a restaurant has a sore throat with fever. Restrict or exclude? | I23: A. Restrict from working with exposed food, utensils, and equipment B. Exclude from the operation | J23: A. Restrict from working with exposed food, utensils, and equipment | K23: Assigned (high confidence) | L23: Sore throat with fever means restricting the food handler; exclusion applies only when the operation primarily serves a high-risk population. | M23: Applying the sore-throat-with-fever rule: restrict at a regular restaurant, exclude only where a high-risk population is served. | O23: Multiple choice
A24: RD-043 | B24: Review Slide Deck | C24: Slide 43 | D24: 3 | E24: The Safe Food Handler | F24: Reporting illness, restricting and excluding | G24: Multiple choice | H24: A food handler has a persistent runny nose. Restrict or exclude? | I24: A. Restrict from working with exposed food, utensils, and equipment B. Exclude from the operation | J24: A. Restrict from working with exposed food, utensils, and equipment | K24: Assigned (high confidence) | L24: Persistent sneezing, coughing, or a runny nose that causes discharges means restricting the food handler from working with exposed food, utensils, and equipment. | M24: Knowing that persistent respiratory symptoms lead to restriction, not exclusion. | O24: Multiple choice
A25: RD-044 | B25: Review Slide Deck | C25: Slide 44 | D25: 3 | E25: The Safe Food Handler | F25: Reporting illness, restricting and excluding | G25: Multiple choice | H25: A food handler is vomiting. Restrict or exclude? | I25: A. Restrict from working with exposed food, utensils, and equipment B. Exclude from the operation | J25: B. Exclude from the operation | K25: Assigned (high confidence) | L25: Vomiting (like diarrhea) means the food handler must be excluded from the operation. | M25: Knowing that vomiting and diarrhea always mean exclusion, the stricter of the two actions. | O25: Multiple choice
A26: RD-045 | B26: Review Slide Deck | C26: Slide 45 | D26: 3 | E26: The Safe Food Handler | F26: Reporting illness, restricting and excluding | G26: Multiple choice | H26: When can food handlers who are vomiting return to work? | I26: A. When they have had no symptoms for at least 24 hours B. When they have a written release from a medical practitioner C. Either A or B | J26: C. Either A or B | K26: Assigned (high confidence) | L26: Food handlers excluded for vomiting or diarrhea can return when they have had no symptoms for at least 24 hours or have a written release from a medical practitioner. | M26: Knowing the return-to-work rule for vomiting: either 24 symptom-free hours or a medical release is enough. | O26: Multiple choice
A27: RD-046 | B27: Review Slide Deck | C27: Slide 46 | D27: 3 | E27: The Safe Food Handler | F27: Reporting illness, restricting and excluding | G27: Multiple choice | H27: When can food handlers who have jaundice return to work? | I27: A. When they have a written release from a medical practitioner B. When they have approval from the health department C. Both A and B | J27: C. Both A and B | K27: Assigned (high confidence) | L27: A food handler with jaundice is excluded and reported, and can return only with approval from the regulatory authority and a written release from a medical practitioner. | M27: Contrasting jaundice with vomiting: jaundice needs both a medical release and regulatory approval, not just one. | O27: Multiple choice
A28: RD-047 | B28: Review Slide Deck | C28: Slide 47 | D28: 3 | E28: The Safe Food Handler | F28: Reporting illness, restricting and excluding | G28: Multiple choice | H28: A food handler has been diagnosed with an illness caused by hepatitis A. What must a manager do? | I28: A. Restrict the food handler from working with exposed food, utensils, and equipment B. Exclude the food handler from the operation | J28: B. Exclude the food handler from the operation | K28: Assigned (high confidence) | L28: A food handler diagnosed with hepatitis A must be excluded from the operation, and the regulatory authority must be notified. | M28: Knowing that a Big Six diagnosis such as hepatitis A means exclusion, not just restriction. | O28: Multiple choice
A29: RD-055 | B29: Review Slide Deck | C29: Slide 55 | D29: 4 | E29: The Flow of Food: An Introduction | F29: Thermometers and calibration | G29: Select all that apply | H29: Which thermometer(s) should be used to check a hamburger patty? Select all that apply. | I29: A. Bimetallic stemmed B. Thermocouple C. Infrared | J29: B: Thermocouple | K29: Assigned (high confidence) | L29: A thin food like a hamburger patty needs a thermocouple or thermistor with a thin probe; a bimetallic stemmed thermometer’s sensing area is too long for thin food, and infrared thermometers only read the surface. | M29: Matching thermometer to food thickness, and knowing infrared can’t measure internal temperature. | O29: Multiple choice (rewritten)
... A38: RD-089 | B38: Review Slide Deck | C38: Slide 89 | D38: 5 | E38: The Flow of Food: Purchasing, Receiving, and Storage | F38: Labeling and date marking | G38: Multiple choice | H38: Tuna salad was prepared on July 5 using tuna with a use-by date of July 8. What is the discard date of the tuna salad? | I38: A. July 5 B. July 8 C. July 11 | J38: B. July 8 | K38: Assigned (high confidence) | L38: When combining ingredients, the discard date is the earliest use-by date of the ingredients. Seven days from July 5 would be July 11, but the tuna’s July 8 use-by date comes first. | M38: Applying the date-marking rule for combined food: the shortest ingredient date wins over the 7-day rule. | O38: Multiple choice
A39: RD-095 | B39: Review Slide Deck | C39: Slide 95 | D39: 5 | E39: The Flow of Food: Purchasing, Receiving, and Storage | F39: Storage temperature, rotation and order | G39: Multiple choice | H39: Salt is stored in a container made for holding food. Is this food being stored correctly? | I39: A. Yes B. No | J39: A. Yes | K39: Assigned (low confidence) | L39: Storing food in a food-grade container is correct. Never re-use single-use containers to store food, never use empty food containers to store chemicals, and never put food in empty chemical containers. | M39: Knowing which containers can hold food: food-grade containers yes; reused single-use containers or chemical containers never. | N39: The slide’s explanation describes the salt as stored in a container intended for food, so it is marked correct; the picture would confirm it. | O39: Multiple choice
A40: RD-103 | B40: Review Slide Deck | C40: Slide 103 | D40: 6 | E40: The Flow of Food: Preparation | F40: Cooling and reheating | G40: Multiple choice | H40: Which food will cool quicker? (The slide shows refried beans and mashed potatoes in two different containers; the picture isn’t in the file.) | I40: A. Refried beans B. Mashed potatoes | J40: Can’t be determined: the slide’s picture isn’t in the file | K40: Not answerable (picture missing) | L40: Stainless steel transfers heat away from food faster than plastic, so the food in the stainless steel container cools quicker. Which food that is depends on the picture. | M40: Knowing that the container’s material affects cooling speed: stainless steel cools food faster than plastic. | O40: Not on the website (picture missing)
A41: RD-114 | B41: Review Slide Deck | C41: Slide 114 | D41: 7 | E41: The Flow of Food: Service | F41: Serving food safely | G41: Multiple choice | H41: Are these food items’ serving utensils being handled safely? (The slide’s picture isn’t in the file.) | I41: A. Yes B. No | J41: B. No | K41: Assigned (low confidence) | L41: Serving utensils should be stored in the food with the handle extended above the rim of the container, or on a clean and sanitized food-contact surface. | M41: Knowing the safe ways to store serving utensils between uses: in the food with the handle above the rim, or on a clean and sanitized surface. | N41: The slide only states the rule; “No” assumes the picture shows utensils stored the wrong way. | O41: Not on the website (picture missing)
A42: RD-116 | B42: Review Slide Deck | C42: Slide 116 | D42: 7 | E42: The Flow of Food: Service | F42: Self-service, off-site service and vending | G42: Multiple choice | H42: Is this food being delivered safely? (The slide’s picture isn’t in the file.) | I42: A. Yes B. No | J42: B. No | K42: Assigned (low confidence) | L42: Food should be delivered in insulated, food-grade containers designed to stop food from mixing, leaking, or spilling. | M42: Knowing what off-site delivery requires: insulated, food-grade containers that keep food separate and contained. | N42: The slide only states the rule; “No” assumes the picture shows food delivered without proper containers. | O42: Not on the website (picture missing)
A43: RD-117 | B43: Review Slide Deck | C43: Slide 117 | D43: 7 | E43: The Flow of Food: Service | F43: Self-service, off-site service and vending | G43: Multiple choice | H43: How often must TCS food in vending machines be checked? | I43: A. Every day B. Every 3 days C. Every 4 days D. Every 7 days | J43: A. Every day | K43: Assigned (medium confidence) | L43: Check the shelf life of products in vending machines daily, and throw out food that is past its use-by or expiration date. | M43: Recalling the daily check for vending machine food. | O43: Multiple choice
A44: RD-126 | B44: Review Slide Deck | C44: Slide 126 | D44: 9 | E44: Safe Facilities and Pest Management | F44: Facility design, plan review and equipment | G44: Multiple choice | H44: You see a sanitation certification mark (such as the NSF mark) on a piece of equipment. What does it mean? | I44: A. It is safe for use with food. B. It is approved by the FDA. | J44: A. It is safe for use with food. | K44: Assigned (medium confidence) | L44: Marks such as NSF, UL EPH, and ETL Sanitation show the equipment has been certified or classified for sanitation under an ANAB-accredited program, so it is safe for use with food. The FDA does not approve equipment. | M44: Knowing what sanitation marks mean, and that they come from ANAB-accredited programs, not FDA approval. | N44: The slide shows a logo that isn’t in the file; the question names the mark in words instead. | O44: Multiple choice
A45: RD-136 | B45: Review Slide Deck | C45: Slide 136 | D45: 9 | E45: Safe Facilities and Pest Management | F45: Water, plumbing and backflow | G45: Multiple choice | H45: What is the best way to prevent backflow? | I45: A. Install a vacuum breaker. B. Install a reduced pressure zone backflow preventer. C. Avoid creating a cross-connection. | J45: C. Avoid creating a cross-connection. | K45: Assigned (high confidence) | L45: The best way to prevent backflow is to avoid creating a cross-connection; mechanical devices such as vacuum breakers are backups. | M45: Knowing that avoiding cross-connections comes first, with devices as backup. The trap is picking a device. | O45: Multiple choice
A46: RD-139 | B46: Review Slide Deck | C46: Slide 139 | D46: 9 | E46: Safe Facilities and Pest Management | F46: Lighting, ventilation, garbage and wastewater | G46: Multiple choice | H46: There is a buildup of grease and condensation on the walls and ceilings. What is the problem? | I46: A. Staff has not been cleaning adequately. B. The ventilation system is not working correctly. C. The grill is not being operated at a high enough temperature. | J46: B. The ventilation system is not working correctly. | K46: Assigned (high confidence) | L46: A buildup of grease and condensation on walls and ceilings is a sign that the ventilation system isn’t working correctly. | M46: Recognizing grease and condensation buildup as a ventilation problem, not a cleaning one. | O46: Multiple choice
A47: RD-157 | B47: Review Slide Deck | C47: Slide 157 | D47: 10 | E47: Cleaning and Sanitizing | F47: Dishwashing | G47: Multiple choice | H47: Silverware has dried-on food. What’s the best thing to do before washing it? | I47: A. Scrape them. B. Rinse them. C. Soak them. | J47: C. Soak them. | K47: Assigned (medium confidence) | L47: Items are normally scraped before washing, and the slide notes they can also be rinsed or presoaked when necessary; dried-on food is the case where presoaking is needed. | M47: Knowing the pre-wash step and when it changes: scrape normally, but presoak items with dried-on food. | N47: The slide’s explanation (scrape, or rinse or presoak if necessary) doesn’t pick one option. | O47: Multiple choice
A48: RD-161 | B48: Review Slide Deck | C48: Slide 161 | D48: 10 | E48: Cleaning and Sanitizing | F48: Storing tableware, cleaning tools and chemicals | G48: Multiple choice | H48: Have these cups been stored correctly? (The slide’s picture isn’t in the file.) | I48: A. Yes B. No | J48: B. No | K48: Assigned (low confidence) | L48: Glasses and cups should be stored upside down on a clean and sanitized shelf or rack. | M48: Knowing that cups and glasses are stored upside down on a clean and sanitized shelf or rack. | N48: The slide only states the rule; “No” assumes the picture shows cups stored the wrong way. | O48: Not on the website (picture missing)

Sheet Website rewrites
A1: ID | B1: Source | C1: Chapter | D1: Original type | E1: Original question | F1: Original answer | G1: Website question (multiple choice) | H1: Website choices | I1: Website answer
A2: AQ01-01 | B2: SSM9E Activity Quiz 1 | C2: 1 | D2: True / false | E2: A food handler’s hands can transfer pathogens from one food to another. | F2: True | G2: How can a food handler’s hands make food unsafe? | H2: A. Hands can only contaminate food if they have a cut B. Hands can carry pathogens from one food to another C. Hands affect food safety only when handling raw meat D. Hands spread pathogens only to food-contact surfaces | I2: B. Hands can carry pathogens from one food to another
A3: AQ01-02 | B3: SSM9E Activity Quiz 1 | C3: 1 | D3: True / false | E3: Food handlers who don’t wash their hands correctly can cause a foodborne illness. | F3: True | G3: What can happen when food handlers don’t wash their hands correctly? | H3: A. Pathogens on their hands can get into food and cause a foodborne illness B. Nothing, as long as they wear gloves for part of the shift C. Only the food handler is at risk of getting sick D. Food quality drops, but food safety is not affected | I3: A. Pathogens on their hands can get into food and cause a foodborne illness
A4: AQ01-03 | B4: SSM9E Activity Quiz 1 | C4: 1 | D4: True / false | E4: A foodborne-illness outbreak is when two or more people get sick after eating at the same place. | F4: False | G4: What is a foodborne-illness outbreak? | H4: A. Two or more people getting sick after eating at the same place, whatever food they ate B. One person getting sick twice after eating at the same restaurant within a week C. Two or more people sick from the same food, confirmed by an investigation D. Any illness that a customer reports to the regulatory authority after eating out | I4: C. Two or more people sick from the same food, confirmed by an investigation
A5: AQ01-04 | B5: SSM9E Activity Quiz 1 | C5: 1 | D5: True / false | E5: Adults are more likely than preschool-age children to get sick from contaminated food. | F5: False | G5: Which group is at higher risk of getting sick from contaminated food? | H5: A. Healthy adults B. Preschool-age children C. Teenagers D. Adults who exercise regularly | I5: B. Preschool-age children
A6: AQ01-05 | B6: SSM9E Activity Quiz 1 | C6: 1 | D6: True / false | E6: Training needs can be identified by watching employee performance. | F6: True | G6: How can a manager identify training needs? | H6: A. By watching employee performance on the job B. By waiting for a regulatory inspection to point them out C. By asking customers to rate employees D. By reviewing employees’ hiring paperwork only | I6: A. By watching employee performance on the job
A7: AQ01-11 | B7: SSM9E Activity Quiz 1 | C7: 1 | D7: Select all that apply | E7: Which of these foods is, or contains, a TCS food? Select every one that applies. | F7: A, C, D, E, F, G, H, I: Baked potatoes; Pizza with diced tomatoes and green pepper; Poached salmon; Refried beans; Scrambled shell eggs; Shrimp fried rice; Tofu ice cream; Vanilla milk shake | G7: Which of these foods is NOT a TCS food? | H7: A. Baked potatoes B. Tofu ice cream C. Whole-wheat bread D. Refried beans | I7: C. Whole-wheat bread
A8: AQ02-01 | B8: SSM9E Activity Quiz 2 | C8: 2 | D8: True / false | E8: All pathogens need oxygen to grow. | F8: False | G8: Which statement about pathogens and oxygen is correct? | H8: A. All pathogens need oxygen to grow B. No pathogen can grow when oxygen is present C. Some pathogens need oxygen to grow, and others grow without it D. Pathogens need oxygen only at refrigeration temperatures | I8: C. Some pathogens need oxygen to grow, and others grow without it
A9: AQ02-02 | B9: SSM9E Activity Quiz 2 | C9: 2 | D9: True / false | E9: The most important way to prevent foodborne illnesses caused by viruses is to control time and temperature. | F9: False | G9: What is the most important way to prevent foodborne illnesses caused by viruses? | H9: A. Controlling time and temperature B. Practicing good personal hygiene C. Cooking all food to 165°F (74°C) D. Freezing food before serving it | I9: B. Practicing good personal hygiene
A10: AQ02-03 | B10: SSM9E Activity Quiz 2 | C10: 2 | D10: True / false | E10: Salmonella Typhi is commonly linked with ground beef. | F10: False | G10: Which food is Salmonella Typhi commonly linked with? | H10: A. Ground beef B. Rice and grains C. Ready-to-eat food and beverages D. Unwashed leafy greens only | I10: C. Ready-to-eat food and beverages
A11: AQ02-04 | B11: SSM9E Activity Quiz 2 | C11: 2 | D11: True / false | E11: Parasites are commonly associated with seafood. | F11: True | G11: Which food are parasites most commonly associated with? | H11: A. Seafood B. Cooked rice C. Bottled water D. Hard cheese | I11: A. Seafood
A12: AQ02-05 | B12: SSM9E Activity Quiz 2 | C12: 2 | D12: True / false | E12: The R in the acronym “Employees FIRST” reminds employees to rotate foods in storage. | F12: False | G12: In the food defense acronym “Employees FIRST,” what does the R stand for? | H12: A. Rotate foods in storage B. Report illness to the manager C. Restrict access to the kitchen D. Recognize anything out of the ordinary | I12: D. Recognize anything out of the ordinary
A13: AQ02-06 | B13: SSM9E Activity Quiz 2 | C13: 2 | D13: True / false | E13: A restaurant must use table tents to notify people of the major allergens in their food. | F13: False | G13: How must a restaurant notify customers about the major allergens in its food? | H13: A. It must place table tents listing the allergens on every table B. It must tell customers, and table tents are only one acceptable way C. It must post one sign at the entrance, and nothing more is needed D. It doesn’t need to unless a customer asks | I13: B. It must tell customers, and table tents are only one acceptable way
... A92: RD-148 | B92: Review Slide Deck | C92: 10 | D92: Put in order | E92: Put the steps for cleaning and sanitizing a surface in order. | F92: 1. Scrape or remove food from the surface.; 2. Wash the surface.; 3. Rinse the surface.; 4. Sanitize the surface.; 5. Allow the surface to air-dry. | G92: What is the correct order for cleaning and sanitizing a surface? | H92: A. Wash → scrape → rinse → sanitize → air-dry B. Scrape → wash → sanitize → rinse → air-dry C. Scrape → wash → rinse → sanitize → air-dry D. Scrape → rinse → wash → sanitize → air-dry | I92: C. Scrape → wash → rinse → sanitize → air-dry

Sheet Topics
A1: Chapter | B1: Topic | C1: Questions
A2: 1 | B2: Foodborne illness and high-risk groups | C2: =COUNTIF(Questions!$F$2:$F$458,B2) -> 3
A3: 1 | B3: How food becomes unsafe | C3: =COUNTIF(Questions!$F$2:$F$458,B3) -> 10
A4: 1 | B4: TCS and ready-to-eat food | C4: =COUNTIF(Questions!$F$2:$F$458,B4) -> 3
A5: 1 | B5: Manager role, training and inspections | C5: =COUNTIF(Questions!$F$2:$F$458,B5) -> 5
A6: 2 | B6: Pathogen growth (FAT TOM) | C6: =COUNTIF(Questions!$F$2:$F$458,B6) -> 6
A7: 2 | B7: Big Six pathogens and linked foods | C7: =COUNTIF(Questions!$F$2:$F$458,B7) -> 15
A8: 2 | B8: Viruses, parasites, fungi and biological toxins | C8: =COUNTIF(Questions!$F$2:$F$458,B8) -> 7
A9: 2 | B9: Chemical and physical contaminants | C9: =COUNTIF(Questions!$F$2:$F$458,B9) -> 1
A10: 2 | B10: Food defense | C10: =COUNTIF(Questions!$F$2:$F$458,B10) -> 4
A11: 2 | B11: Responding to an outbreak | C11: =COUNTIF(Questions!$F$2:$F$458,B11) -> 1
A12: 2 | B12: Food allergens and cross-contact | C12: =COUNTIF(Questions!$F$2:$F$458,B12) -> 14
A13: 3 | B13: Handwashing and hand care | C13: =COUNTIF(Questions!$F$2:$F$458,B13) -> 13
... A46: 10 | B46: Cleaning programs and chemical use | C46: =COUNTIF(Questions!$F$2:$F$458,B46) -> 6
B47: Total | C47: =SUM(C2:C46) -> 457
